Workbook

Sheet Hoja1
A1: Módulo / Atlas de Igualdad y Derechos Humanos | M1: 45536
A2: LISTADO DE INDICADORES Y SUS FICHAS TÉCNICAS
A4: Comisión Nacional de Derechos Humanos I Cuarta Visitaduría General I Programa de Asunto de la Mujer y de Igualdad entre Mujeres y Hombres
A5: Dirección General de Planeación y Estrategia Institucional I Centro de Análisis de Información Geoespacial
A6: ATLAS | E6: FICHAS TÉCNICAS
A8: ID | B8: Dimensión | C8: Indicador | D8: Subindicador I | E8: Nombre: | F8: Datos disponibles: | G8: Desagregación geográfica: | H8: Definición: | I8: Desagregación: | J8: Forma de cálculo: | K8: Unidad del Estado responsable del cálculo: | L8: Unidad de medida: | M8: Periodicidad: | N8: Fuente de información: | O8: Articulación jurídica: | P8: Observaciones: | Q8: Consideraciones
A9: 1 | B9: Demográfica | C9: Población por sexo | D9: Población estatal | E9: =[1]Demográfica!D4 -> Población por entidad federativa. | F9: =[1]Demográfica!E4 -> 2005, 2010, 2015 y 2020. | G9: =[1]Demográfica!F4 -> Estatal | H9: =[1]Demográfica!G4 -> Total de población que reside habitualmente en la vivienda en la fecha de referencia al levantamiento por entidad federativa. | I9: =[1]Demográfica!H4 -> No aplica. | J9: =[1]Demográfica!I4 -> Suma de la población total (con estimación) de la unidad administrativa. | K9: =[1]Demográfica!J4 -> Cálculos por el Colegio de Geografía (UNAM) y de la CNDH a partir de la información del Instituto Nacional de Estadística y Geografía (INEGI) | L9: =[1]Demográfica!K4 -> Absolutos | ... P9: =[1]Demográfica!O4 -> Notas INEGI: Derivado de la sentencia emitida por el Pleno de la Suprema Corte de Justicia de la Nación respecto a la Controversia Constitucional 41/2011, se publican, con fecha 26 de junio de 2013, todos los resultados del Censo de Población y Vivienda 2010 para los municipios de Tultepec, Nextlalpan y Tultitlán, estado de México. Para 2020, la información está referida al 15 de marzo. Incluye una estimación de población de 6 337 751 personas que corresponden a 1 588 422 Viviendas sin información de ocupantes. | Q9: =[1]Demográfica!AD4 -> Datos vigentes por periodicidad quinquenal.
A10: 2 | B10: Demográfica | C10: Población por sexo | D10: Población estatal de mujeres | E10: =[1]Demográfica!D5 -> Población de mujeres, por entidad federativa. | F10: =[1]Demográfica!E5 -> 2005, 2010, 2015 y 2020. | G10: =[1]Demográfica!F5 -> Estatal | H10: =[1]Demográfica!G5 -> Total de población de mujeres que reside habitualmente en la vivienda en la fecha de referencia al levantamiento por entidad federativa. | I10: =[1]Demográfica!H5 -> Por sexo | J10: =[1]Demográfica!I5 -> Suma de la población según sexo (mujeres/hombres) (con estimación) de la unidad administrativa. | K10: =[1]Demográfica!J5 -> Cálculos por el Colegio de Geografía (UNAM) y de la CNDH a partir de la información del Instituto Nacional de Estadística y Geografía (INEGI) | L10: =[1]Demográfica!K5 -> Absolutos | ... P10: =[1]Demográfica!O5 -> Notas INEGI: Derivado de la sentencia emitida por el Pleno de la Suprema Corte de Justicia de la Nación respecto a la Controversia Constitucional 41/2011, se publican, con fecha 26 de junio de 2013, todos los resultados del Censo de Población y Vivienda 2010 para los municipios de Tultepec, Nextlalpan y Tultitlán, estado de México. Para 2020, la información está referida al 15 de marzo. Incluye una estimación de población de 6 337 751 personas que corresponden a 1 588 422 Viviendas sin información de ocupantes. | Q10: =[1]Demográfica!AD5 -> Datos vigentes por periodicidad quinquenal.
A11: 3 | B11: Demográfica | C11: Población por sexo | D11: Población estatal de hombres | E11: =[1]Demográfica!D6 -> Población de hombres, por entidad federativa. | F11: =[1]Demográfica!E6 -> 2005, 2010, 2015 y 2020. | G11: =[1]Demográfica!F6 -> Estatal | H11: =[1]Demográfica!G6 -> Total de población de hombres que reside habitualmente en la vivienda en la fecha de referencia al levantamiento por entidad federativa. | I11: =[1]Demográfica!H6 -> Por sexo | J11: =[1]Demográfica!I6 -> Suma de la población según sexo (mujeres/hombres) (con estimación) de la unidad administrativa. | K11: =[1]Demográfica!J6 -> Cálculos por el Colegio de Geografía (UNAM) y de la CNDH a partir de la información del Instituto Nacional de Estadística y Geografía (INEGI) | L11: =[1]Demográfica!K6 -> Absolutos | ... P11: =[1]Demográfica!O6 -> Notas INEGI: Derivado de la sentencia emitida por el Pleno de la Suprema Corte de Justicia de la Nación respecto a la Controversia Constitucional 41/2011, se publican, con fecha 26 de junio de 2013, todos los resultados del Censo de Población y Vivienda 2010 para los municipios de Tultepec, Nextlalpan y Tultitlán, estado de México. Para 2020, la información está referida al 15 de marzo. Incluye una estimación de población de 6 337 751 personas que corresponden a 1 588 422 Viviendas sin información de ocupantes. | Q11: =[1]Demográfica!AD6 -> Datos vigentes por periodicidad quinquenal.
A12: 4 | B12: Demográfica | C12: Población que habla lengua indígena por sexo | D12: Población estatal que habla lengua indígena | E12: =[1]Demográfica!D7 -> Población que habla lengua indígena, por entidad federativa. | F12: =[1]Demográfica!E7 -> 2005, 2010, 2015 y 2020. | G12: =[1]Demográfica!F7 -> Estatal | H12: =[1]Demográfica!G7 -> Total de población de 5 años y más (o 3 años y más, cuando corresponda) que habla lengua indígena, incluyendo lenguas originarias de otros países Latinoamericanos, en la fecha de referencia al levantamiento por entidad federativa. | I12: =[1]Demográfica!H7 -> No aplica. | J12: =[1]Demográfica!I7 -> Suma de la población total de 5 años y más (o 3 años y más, cuando corresponda) que habla lengua indígena. | K12: =[1]Demográfica!J7 -> Cálculos por el Colegio de Geografía (UNAM) y de la CNDH a partir de la información del Instituto Nacional de Estadística y Geografía (INEGI) | L12: =[1]Demográfica!K7 -> Absolutos | ... P12: =[1]Demográfica!O7 -> Para 2005 la información está referida a la población de 5 años y más, mientras que para 2010 para la población de 3 años y más. Nota INEGI: Derivado de la sentencia emitida por el Pleno de la Suprema Corte de Justicia de la Nación respecto a la Controversia Constitucional 41/2011, se publican, con fecha 26 de junio de 2013, todos los resultados del Censo de Población y Vivienda 2010 para los municipios de Tultepec, Nextlalpan y Tultitlán, estado de México. | Q12: =[1]Demográfica!AD7 -> Datos vigentes por periodicidad quinquenal.
A13: 5 | B13: Demográfica | C13: Población que habla lengua indígena por sexo | D13: Población estatal de mujeres que habla lengua indígena | E13: =[1]Demográfica!D8 -> Población de mujeres que habla lengua indígena, por entidad federativa. | F13: =[1]Demográfica!E8 -> 2005, 2010, 2015 y 2020. | G13: =[1]Demográfica!F8 -> Estatal | H13: =[1]Demográfica!G8 -> Total de población de niñas y mujeres de 5 años y más (o 3 años y más, cuando corresponda) que hablan lengua indígena, incluyendo lenguas originarias de otros países Latinoamericanos, en la fecha de referencia al levantamiento por entidad federativa. | I13: =[1]Demográfica!H8 -> Por sexo | J13: =[1]Demográfica!I8 -> Suma de la población según sexo (mujeres/hombres) de 5 años y más (o 3 años y más, cuando corresponda) que habla lengua indígena. | K13: =[1]Demográfica!J8 -> Cálculos por el Colegio de Geografía (UNAM) y de la CNDH a partir de la información del Instituto Nacional de Estadística y Geografía (INEGI) | L13: =[1]Demográfica!K8 -> Absolutos | ... P13: =[1]Demográfica!O8 -> Para 2005 la información está referida a la población de 5 años y más, mientras que para 2010 para la población de 3 años y más. Nota INEGI: Derivado de la sentencia emitida por el Pleno de la Suprema Corte de Justicia de la Nación respecto a la Controversia Constitucional 41/2011, se publican, con fecha 26 de junio de 2013, todos los resultados del Censo de Población y Vivienda 2010 para los municipios de Tultepec, Nextlalpan y Tultitlán, estado de México. | Q13: =[1]Demográfica!AD8 -> Datos vigentes por periodicidad quinquenal.
A14: 6 | B14: Demográfica | C14: Población que habla lengua indígena por sexo | D14: Población estatal de hombres que habla lengua indígena | E14: =[1]Demográfica!D9 -> Población de hombres que habla lengua indígena, por entidad federativa. | F14: =[1]Demográfica!E9 -> 2005, 2010, 2015 y 2020. | G14: =[1]Demográfica!F9 -> Estatal | H14: =[1]Demográfica!G9 -> Total de población de niños y hombres de 5 años y más (o 3 años y más, cuando corresponda) que hablan lengua indígena, incluyendo lenguas originarias de otros países Latinoamericanos, en la fecha de referencia al levantamiento por entidad federativa. | I14: =[1]Demográfica!H9 -> Por sexo | J14: =[1]Demográfica!I9 -> Suma de la población según sexo (mujeres/hombres) de 5 años y más (o 3 años y más, cuando corresponda) que habla lengua indígena. | K14: =[1]Demográfica!J9 -> Cálculos por el Colegio de Geografía (UNAM) y de la CNDH a partir de la información del Instituto Nacional de Estadística y Geografía (INEGI) | L14: =[1]Demográfica!K9 -> Absolutos | ... P14: =[1]Demográfica!O9 -> Para 2005 la información está referida a la población de 5 años y más, mientras que para 2010 para la población de 3 años y más. Nota INEGI: Derivado de la sentencia emitida por el Pleno de la Suprema Corte de Justicia de la Nación respecto a la Controversia Constitucional 41/2011, se publican, con fecha 26 de junio de 2013, todos los resultados del Censo de Población y Vivienda 2010 para los municipios de Tultepec, Nextlalpan y Tultitlán, estado de México. | Q14: =[1]Demográfica!AD9 -> Datos vigentes por periodicidad quinquenal.
A15: 7 | B15: Demográfica | C15: Densidad de población | D15: Densidad de población estatal | E15: =[1]Demográfica!D10 -> Densidad de población, por entidad federativa. | F15: =[1]Demográfica!E10 -> 2005, 2010, 2015 y 2020. | G15: =[1]Demográfica!F10 -> Estatal | H15: =[1]Demográfica!G10 -> Número de habitantes en función del área de un territorio determinado por kilómetro cuadrado, en la fecha de referencia al levantamiento por entidad federativa. | I15: =[1]Demográfica!H10 -> No aplica. | J15: =[1]Demográfica!I10 -> Cociente de la población total entre la superficie de la unidad administrativa. | K15: =[1]Demográfica!J10 -> Cálculos por el Colegio de Geografía (UNAM) y de la CNDH a partir de la información del Instituto Nacional de Estadística y Geografía (INEGI) | L15: =[1]Demográfica!K10 -> Habitantes por kilómetro cuadrado | ... P15: =[1]Demográfica!O10 -> 0 | Q15: =[1]Demográfica!AD10 -> Datos vigentes por periodicidad quinquenal.
A16: 8 | B16: Demográfica | C16: Índice de envejecimiento | D16: Índice de envejecimiento estatal | E16: =[1]Demográfica!D11 -> Índice de envejecimiento, por entidad federativa. | F16: =[1]Demográfica!E11 -> 2005, 2010, 2015 y 2020 | G16: =[1]Demográfica!F11 -> Estatal | H16: =[1]Demográfica!G11 -> Relación entre la cantidad de personas mayores (65 años y más) y la cantidad de personas en la niñez y adolescencia (0 a 14 años de edad), en la fecha de referencia al levantamiento por entidad federativa. | I16: =[1]Demográfica!H11 -> No aplica. | J16: =[1]Demográfica!I11 -> Suma de la población total de 65 años y más, entre la población total de 0 a 14 años, multiplicado por 100. | K16: =[1]Demográfica!J11 -> Cálculos por el Colegio de Geografía (UNAM) y de la CNDH a partir de la información del Instituto Nacional de Estadística y Geografía (INEGI) | L16: =[1]Demográfica!K11 -> Porcentaje | ... P16: =[1]Demográfica!O11 -> 0 | Q16: =[1]Demográfica!AD11 -> Datos vigentes por periodicidad quinquenal.
A17: 9 | B17: Demográfica | C17: Índice de envejecimiento | D17: Índice de envejecimiento estatal de mujeres | E17: =[1]Demográfica!D12 -> Índice de envejecimiento de mujeres, por entidad federativa. | F17: =[1]Demográfica!E12 -> 2005, 2010, 2015 y 2020 | G17: =[1]Demográfica!F12 -> Estatal | H17: =[1]Demográfica!G12 -> Relación entre la cantidad de mujeres mayores (65 años y más) y la cantidad de niñas y adolescentes (0 a 14 años de edad) en la fecha de referencia al levantamiento por entidad federativa. | I17: =[1]Demográfica!H12 -> Por sexo | J17: =[1]Demográfica!I12 -> Suma de la población total de mujeres de 65 años y más, entre la población total de niñas de 0 a 14 años, multiplicado por 100. | K17: =[1]Demográfica!J12 -> Cálculos por el Colegio de Geografía (UNAM) y de la CNDH a partir de la información del Instituto Nacional de Estadística y Geografía (INEGI) | L17: =[1]Demográfica!K12 -> Porcentaje | ... P17: =[1]Demográfica!O12 -> 0 | Q17: =[1]Demográfica!AD12 -> Datos vigentes por periodicidad quinquenal.
A18: 10 | B18: Demográfica | C18: Índice de envejecimiento | D18: Índice de envejecimiento estatal de hombres | E18: =[1]Demográfica!D13 -> Índice de envejecimiento de hombres, por entidad federativa. | F18: =[1]Demográfica!E13 -> 2005, 2010, 2015 y 2020 | G18: =[1]Demográfica!F13 -> Estatal | H18: =[1]Demográfica!G13 -> Relación entre la cantidad de hombres mayores (65 años y más) y la cantidad de niños y adolescentes (0 a 14 años de edad), en la fecha de referencia al levantamiento por entidad federativa. | I18: =[1]Demográfica!H13 -> Por sexo | J18: =[1]Demográfica!I13 -> Suma de la población total de hombres de 65 años y más, entre la población total de niños de 0 a 14 años, multiplicado por 100. | K18: =[1]Demográfica!J13 -> Cálculos por el Colegio de Geografía (UNAM) y de la CNDH a partir de la información del Instituto Nacional de Estadística y Geografía (INEGI) | L18: =[1]Demográfica!K13 -> Porcentaje | ... P18: =[1]Demográfica!O13 -> 0 | Q18: =[1]Demográfica!AD13 -> Datos vigentes por periodicidad quinquenal.
A19: 11 | B19: Demográfica | C19: Relación de dependencia | D19: Relación de dependencia estatal | E19: =[1]Demográfica!D14 -> Relación de dependencia, por entidad federativa. | F19: =[1]Demográfica!E14 -> 2005, 2010, 2015 y 2020. | G19: =[1]Demográfica!F14 -> Estatal | H19: =[1]Demográfica!G14 -> Relación entre el total de personas en edad económicamente inactiva (niños, niñas, adolescentes [0 a 14 años] y personas mayores [60 años y más]) y el total de personas en edad económicamente activa [15 a 59 años], en la fecha de referencia al levantamiento por entidad federativa. | I19: =[1]Demográfica!H14 -> No aplica. | J19: =[1]Demográfica!I14 -> Suma de la población total de 0 a 14 años más la población total de 60 años y más, entre la población total de 15 a 59, multiplicado por 100. [Por edad: dependencia infantil -en el numerador sólo se toma a la población de 0 a 14 años- y dependencia de adultos mayores -en el numerador sólo se toma a la población de 60 y más años). | K19: =[1]Demográfica!J14 -> Cálculos por el Colegio de Geografía (UNAM) y de la CNDH a partir de la información del Instituto Nacional de Estadística y Geografía (INEGI) | L19: =[1]Demográfica!K14 -> Porcentaje | ... P19: =[1]Demográfica!O14 -> Se trata de una relación potencial puesto que no todas las personas menores de 14 o mayores de 60 años está fuera del mercado laboral, ni todas las de 14-60 son activas (de hecho, la dependencia efectiva suele ser superior). No obstante, resume de manera aproximada la relación entre la magnitud de la fuerza de trabajo y la población pasiva, insumo a tener en cuenta en la formulación de políticas de empleo y de previsión social. | Q19: =[1]Demográfica!AD14 -> Datos vigentes por periodicidad quinquenal.
A20: 12 | B20: Demográfica | C20: Relación de dependencia | D20: Relación de dependencia estatal infantil | E20: =[1]Demográfica!D15 -> Relación de dependencia infantil, por entidad federativa. | F20: =[1]Demográfica!E15 -> 2005, 2010, 2015 y 2020. | G20: =[1]Demográfica!F15 -> Estatal | H20: =[1]Demográfica!G15 -> Relación entre el total de niñas, niños y adolescentes en edad económicamente inactiva [0 a 14 años] y el total de personas en edad económicamente activa [15 a 59 años], en la fecha de referencia al levantamiento por entidad federativa. | I20: =[1]Demográfica!H15 -> No aplica. | J20: =[1]Demográfica!I15 -> Suma de la población total de 0 a 14 años más la población total de 60 años y más, entre la población total de 15 a 59, multiplicado por 100. [Por edad: dependencia infantil -en el numerador sólo se toma a la población de 0 a 14 años- y dependencia de adultos mayores -en el numerador sólo se toma a la población de 60 y más años). | K20: =[1]Demográfica!J15 -> Cálculos por el Colegio de Geografía (UNAM) y de la CNDH a partir de la información del Instituto Nacional de Estadística y Geografía (INEGI) | L20: =[1]Demográfica!K15 -> Porcentaje | ... P20: =[1]Demográfica!O15 -> Se trata de una relación potencial puesto que no todas las personas menores de 14 o mayores de 60 años está fuera del mercado laboral, ni todas las de 14-60 son activas (de hecho, la dependencia efectiva suele ser superior). No obstante, resume de manera aproximada la relación entre la magnitud de la fuerza de trabajo y la población pasiva, insumo a tener en cuenta en la formulación de políticas de empleo y de previsión social. | Q20: =[1]Demográfica!AD15 -> Datos vigentes por periodicidad quinquenal.
... A30: 22 | B30: Demográfica | C30: Población con limitación y discapacidad según sexo | D30: Porcentaje estatal de hombres con limitación y discapacidad | E30: =[1]Demográfica!D25 -> Porcentaje de hombres con limitación y discapacidad, por entidad federativa. | F30: =[1]Demográfica!E25 -> 2014, 2018 y 2023 | G30: =[1]Demográfica!F25 -> Estatal | H30: =[1]Demográfica!G25 -> Distribución porcentual de hombres con alguna limitación, discapacidad o algún problema o condición mental, en la fecha de referencia al levantamiento por entidad federativa. | I30: =[1]Demográfica!H25 -> Por sexo | J30: =[1]Demográfica!I25 -> Suma de la población según sexo (mujeres/hombres) con alguna limitación, discapacidad o algún problema o condición mental, entre la población total según sexo (mujeres/hombres), multiplicado por 100. | K30: =[1]Demográfica!J25 -> Cálculos por el Colegio de Geografía (UNAM) y de la CNDH a partir de la información del Instituto Nacional de Estadística y Geografía (INEGI) | L30: =[1]Demográfica!K25 -> Porcentaje | ... P30: =[1]Demográfica!O25 -> La variable es la suma de "con discapacidad y con limitación". | Q30: =[1]Demográfica!AD25 -> Datos vigentes por periodicidad quinquenal.
A31: 23 | B31: Económica | C31: Población Económicamente Activa por grupo de edad según sexo | D31: Porcentaje estatal de mujeres económicamente activas de 20 a 29 años | E31: =[1]Económica!E4 -> Porcentaje de mujeres de 20 a 29 años de edad económicamente activa, por entidad federativa. | F31: =[1]Económica!F4 -> 2005, 2010, 2015 y 2020. | G31: =[1]Económica!G4 -> Estatal | H31: =[1]Económica!H4 -> Distribución porcentual de mujeres de 20 a 29 años de edad económicamente activa, es decir, que tuvieron vínculo con la actividad económica o que lo buscaron en la semana de referencia, por lo que se encontraban ocupadas o desocupadas, en la fecha de referencia al levantamiento por entidad federativa. | I31: =[1]Económica!I4 -> Por sexo y grupo de edad. | J31: =[1]Económica!J4 -> Promedio anual de la población económicamente activa según sexo (mujeres/hombres) y por grupos de edad correspondiente, entre el promedio anual de la población económicamente activa total, multiplicado por 100. | K31: =[1]Económica!K4 -> Cálculos por el Colegio de Geografía (UNAM) y de la CNDH a partir de la información del Instituto Nacional de Estadística y Geografía (INEGI) | L31: =[1]Económica!L4 -> Porcentaje | ... P31: =[1]Económica!P4 -> 1. Para el 2020, el promedio no integra el 2o trimestre por suspensión de la ENOE por contigencia sanitaria de COVID-19. 2. La fuente de información tiene periodicidad trimestral, pero para hacer manejable la cantidad de información, se determinó tomarla de manera quinquenal. | Q31: =[1]Económica!AE4 -> Datos vigentes por periodicidad quinquenal. La fuente de información tiene periodicidad trimestral, pero para hacer manejable la cantidad de información, se determinó tomarla de manera quinquenal.
A32: 24 | B32: Económica | C32: Población Económicamente Activa por grupo de edad según sexo | D32: Porcentaje estatal de hombres económicamente activos de 20 a 29 años | E32: =[1]Económica!E5 -> Porcentaje de hombres de 20 a 29 años de edad económicamente activa, por entidad federativa. | F32: =[1]Económica!F5 -> 2005, 2010, 2015 y 2020. | G32: =[1]Económica!G5 -> Estatal | H32: =[1]Económica!H5 -> Distribución porcentual de hombres de 20 a 29 años de edad económicamente activa, es decir, que tuvieron vínculo con la actividad económica o que lo buscaron en la semana de referencia, por lo que se encontraban ocupadas o desocupadas, en la fecha de referencia al levantamiento por entidad federativa. | I32: =[1]Económica!I5 -> Por sexo y grupo de edad. | J32: =[1]Económica!J5 -> Promedio anual de la población económicamente activa según sexo (mujeres/hombres) y por grupos de edad correspondiente, entre el promedio anual de la población económicamente activa total, multiplicado por 100. | K32: =[1]Económica!K5 -> Cálculos por el Colegio de Geografía (UNAM) y de la CNDH a partir de la información del Instituto Nacional de Estadística y Geografía (INEGI) | L32: =[1]Económica!L5 -> Porcentaje | ... P32: =[1]Económica!P5 -> 1. Para el 2020, el promedio no integra el 2o trimestre por suspensión de la ENOE por contigencia sanitaria de COVID-19. 2. La fuente de información tiene periodicidad trimestral, pero para hacer manejable la cantidad de información, se determinó tomarla de manera quinquenal. | Q32: =[1]Económica!AE5 -> Datos vigentes por periodicidad quinquenal. La fuente de información tiene periodicidad trimestral, pero para hacer manejable la cantidad de información, se determinó tomarla de manera quinquenal.
A33: 25 | B33: Económica | C33: Población asalariada y no asalariada según sexo | D33: Porcentaje estatal de la población trabajadora asalariada | E33: =[1]Económica!E6 -> Porcentaje de población trabajadora subordinada remunerada asalariada, por entidad federativa. | F33: =[1]Económica!F6 -> 2005, 2010, 2015 y 2020. | G33: =[1]Económica!G6 -> Estatal | H33: =[1]Económica!H6 -> Distribución porcentual de la población de 15 y más años de edad, que trabajaron para un patrón o empleador del sector privado o público; y que reciben un pago, sueldo, salario o jornal (subordinadas y remuneradas), en la fecha de referencia al levantamiento por entidad federativa. | I33: =[1]Económica!I6 -> Por posición en el trabajo. | J33: =[1]Económica!J6 -> Promedio anual de la población de 15 y más años de edad ocupada subordinada remunerada asalariada, es decir, que trabajaron para un patrón o empleador del sector privado o público; y que reciben un pago, sueldo, salario o jornal (subordinadas y remuneradas), entre el promedio anual de la población ocupada de cada entidad federativa (de los 4 trimestres) multiplicado por 100. | K33: =[1]Económica!K6 -> Cálculos por el Colegio de Geografía (UNAM) y de la CNDH a partir de la información del Instituto Nacional de Estadística y Geografía (INEGI) | L33: =[1]Económica!L6 -> Porcentaje | ... P33: =[1]Económica!P6 -> 1. Para el 2020, el promedio no integra el 2o trimestre por suspensión de la ENOE por contigencia sanitaria de COVID-19. 2. La fuente de información tiene periodicidad trimestral, pero para hacer manejable la cantidad de información, se determinó tomarla de manera quinquenal. | Q33: =[1]Económica!AE6 -> Datos vigentes por periodicidad quinquenal. La fuente de información tiene periodicidad trimestral, pero para hacer manejable la cantidad de información, se determinó tomarla de manera quinquenal.
A34: 26 | B34: Económica | C34: Población asalariada y no asalariada según sexo | D34: Porcentaje estatal de mujeres trabajadoras asalariadas | E34: =[1]Económica!E7 -> Porcentaje de mujeres trabajadoras subordinadas remuneradas asalariadas, por entidad federativa. | F34: =[1]Económica!F7 -> 2005, 2010, 2015 y 2020. | G34: =[1]Económica!G7 -> Estatal | H34: =[1]Económica!H7 -> Distribución porcentual de mujeres de 15 y más años de edad, que trabajaron para un patrón o empleador del sector privado o público; y que reciben un pago, sueldo, salario o jornal (subordinadas y remuneradas), en la fecha de referencia al levantamiento por entidad federativa. | I34: =[1]Económica!I7 -> Por sexo y posición en el trabajo. | J34: =[1]Económica!J7 -> Promedio anual de la población según sexo (mujeres/hombres) de 15 y más años de edad pcuáda subordinada remunerada asalariada, es decir, que trabajaron para un patrón o empleador del sector privado o público; y que reciben un pago, sueldo, salario o jornal (subordinadas y remuneradas), entre el promedio anual de la población ocupada de cada entidad federativa (de los 4 trimestres) multiplicado por 100. | K34: =[1]Económica!K7 -> Cálculos por el Colegio de Geografía (UNAM) y de la CNDH a partir de la información del Instituto Nacional de Estadística y Geografía (INEGI) | L34: =[1]Económica!L7 -> Porcentaje | ... P34: =[1]Económica!P7 -> 1. Para el 2020, el promedio no integra el 2o trimestre por suspensión de la ENOE por contigencia sanitaria de COVID-19. 2. La fuente de información tiene periodicidad trimestral, pero para hacer manejable la cantidad de información, se determinó tomarla de manera quinquenal. | Q34: =[1]Económica!AE7 -> Datos vigentes por periodicidad quinquenal. La fuente de información tiene periodicidad trimestral, pero para hacer manejable la cantidad de información, se determinó tomarla de manera quinquenal.
A35: 27 | B35: Económica | C35: Población asalariada y no asalariada según sexo | D35: Porcentaje estatal de hombres trabajadores asalariados | E35: =[1]Económica!E8 -> Porcentaje de hombres trabajadores subordinados remunerados asalariados, por entidad federativa. | F35: =[1]Económica!F8 -> 2005, 2010, 2015 y 2020. | G35: =[1]Económica!G8 -> Estatal | H35: =[1]Económica!H8 -> Distribución porcentual de hombres de 15 y más años de edad, que trabajaron para un patrón o empleador del sector privado o público; y que reciben un pago, sueldo, salario o jornal (subordinadas y remuneradas), en la fecha de referencia al levantamiento por entidad federativa. | I35: =[1]Económica!I8 -> Por sexo y posición en el trabajo. | J35: =[1]Económica!J8 -> Promedio anual de la población según sexo (mujeres/hombres) de 15 y más años de edad pcuáda subordinada remunerada asalariada, es decir, que trabajaron para un patrón o empleador del sector privado o público; y que reciben un pago, sueldo, salario o jornal (subordinadas y remuneradas), entre el promedio anual de la población ocupada de cada entidad federativa (de los 4 trimestres) multiplicado por 100. | K35: =[1]Económica!K8 -> Cálculos por el Colegio de Geografía (UNAM) y de la CNDH a partir de la información del Instituto Nacional de Estadística y Geografía (INEGI) | L35: =[1]Económica!L8 -> Porcentaje | ... P35: =[1]Económica!P8 -> 1. Para el 2020, el promedio no integra el 2o trimestre por suspensión de la ENOE por contigencia sanitaria de COVID-19. 2. La fuente de información tiene periodicidad trimestral, pero para hacer manejable la cantidad de información, se determinó tomarla de manera quinquenal. | Q35: =[1]Económica!AE8 -> Datos vigentes por periodicidad quinquenal. La fuente de información tiene periodicidad trimestral, pero para hacer manejable la cantidad de información, se determinó tomarla de manera quinquenal.
A36: 28 | B36: Económica | C36: Población asalariada y no asalariada según sexo | D36: Porcentaje estatal de la población trabajadora con percepciones no salariales | E36: =[1]Económica!E9 -> Porcentaje de población trabajadora con percepciones no salariales, por entidad federativa. | F36: =[1]Económica!F9 -> 2005, 2010, 2015 y 2020. | G36: =[1]Económica!G9 -> Estatal | H36: =[1]Económica!H9 -> Distribución porcentual de población de 15 y más años de edad, que trabajaron en su propio negocio, empresa, establecimiento o predio agrícola (incluye a las personas que trabajaron sin pago en el negocio o predio familiar o no familiar) (subordinadas y remuneradas), en la fecha de referencia al levantamiento por entidad federativa. | I36: =[1]Económica!I9 -> Por posición en el trabajo. | J36: =[1]Económica!J9 -> Promedio anual de la población de 15 y más años de edad ocupada subordinada remunerada no asalariada, es decir, que trabajaron en su propio negocio, empresa, establecimiento o predio agrícola (incluye a las personas que trabajaron sin pago en el negocio o predio familiar o no familiar) (subordinadas y remuneradas), entre el total de la población ocupada de cada entidad federativa, multiplicado por 100. | K36: =[1]Económica!K9 -> Cálculos por el Colegio de Geografía (UNAM) y de la CNDH a partir de la información del Instituto Nacional de Estadística y Geografía (INEGI) | L36: =[1]Económica!L9 -> Porcentaje | ... P36: =[1]Económica!P9 -> 1. Para el 2020, el promedio no integra el 2o trimestre por suspensión de la ENOE por contigencia sanitaria de COVID-19. 2. La fuente de información tiene periodicidad trimestral, pero para hacer manejable la cantidad de información, se determinó tomarla de manera quinquenal. | Q36: =[1]Económica!AE9 -> Datos vigentes por periodicidad quinquenal. La fuente de información tiene periodicidad trimestral, pero para hacer manejable la cantidad de información, se determinó tomarla de manera quinquenal.
A37: 29 | B37: Económica | C37: Población asalariada y no asalariada según sexo | D37: Porcentaje estatal de mujeres trabajadoras con percepciones no salariales | E37: =[1]Económica!E10 -> Porcentaje de mujeres trabajadoras con percepciones no salariales, por entidad federativa. | F37: =[1]Económica!F10 -> 2005, 2010, 2015 y 2020. | G37: =[1]Económica!G10 -> Estatal | H37: =[1]Económica!H10 -> Distribución porcentual de mujeres de 15 y más años de edad, que trabajaron en su propio negocio, empresa, establecimiento o predio agrícola (incluye a las personas que trabajaron sin pago en el negocio o predio familiar o no familiar) (subordinadas y remuneradas), en la fecha de referencia al levantamiento por entidad federativa. | I37: =[1]Económica!I10 -> Por sexo y posición en el trabajo. | J37: =[1]Económica!J10 -> Promedio anual de la población según sexo (mujeres/hombres) de 15 y más años de edad ocupada subordinada remunerada no asalariada, es decir, que trabajaron en su propio negocio, empresa, establecimiento o predio agrícola (incluye a las personas que trabajaron sin pago en el negocio o predio familiar o no familiar) (subordinadas y remuneradas), entre el total de la población ocupada de cada entidad federativa, multiplicado por 100. | K37: =[1]Económica!K10 -> Cálculos por el Colegio de Geografía (UNAM) y de la CNDH a partir de la información del Instituto Nacional de Estadística y Geografía (INEGI) | L37: =[1]Económica!L10 -> Porcentaje | ... P37: =[1]Económica!P10 -> 1. Para el 2020, el promedio no integra el 2o trimestre por suspensión de la ENOE por contigencia sanitaria de COVID-19. 2. La fuente de información tiene periodicidad trimestral, pero para hacer manejable la cantidad de información, se determinó tomarla de manera quinquenal. | Q37: =[1]Económica!AE10 -> Datos vigentes por periodicidad quinquenal. La fuente de información tiene periodicidad trimestral, pero para hacer manejable la cantidad de información, se determinó tomarla de manera quinquenal.
A38: 30 | B38: Económica | C38: Población asalariada y no asalariada según sexo | D38: Porcentaje estatal de hombres trabajadores con percepciones no salariales | E38: =[1]Económica!E11 -> Porcentaje de hombres trabajadores con percepciones no salariales, por entidad federativa. | F38: =[1]Económica!F11 -> 2005, 2010, 2015 y 2020. | G38: =[1]Económica!G11 -> Estatal | H38: =[1]Económica!H11 -> Distribución porcentual de hombres de 15 y más años de edad, que trabajaron en su propio negocio, empresa, establecimiento o predio agrícola (incluye a las personas que trabajaron sin pago en el negocio o predio familiar o no familiar) (subordinadas y remuneradas), en la fecha de referencia al levantamiento por entidad federativa. | I38: =[1]Económica!I11 -> Por sexo y posición en el trabajo. | J38: =[1]Económica!J11 -> Promedio anual de la población según sexo (mujeres/hombres) de 15 y más años de edad ocupada subordinada remunerada no asalariada, es decir, que trabajaron en su propio negocio, empresa, establecimiento o predio agrícola (incluye a las personas que trabajaron sin pago en el negocio o predio familiar o no familiar) (subordinadas y remuneradas), entre el total de la población ocupada de cada entidad federativa, multiplicado por 100. | K38: =[1]Económica!K11 -> Cálculos por el Colegio de Geografía (UNAM) y de la CNDH a partir de la información del Instituto Nacional de Estadística y Geografía (INEGI) | L38: =[1]Económica!L11 -> Porcentaje | ... P38: =[1]Económica!P11 -> 1. Para el 2020, el promedio no integra el 2o trimestre por suspensión de la ENOE por contigencia sanitaria de COVID-19. 2. La fuente de información tiene periodicidad trimestral, pero para hacer manejable la cantidad de información, se determinó tomarla de manera quinquenal. | Q38: =[1]Económica!AE11 -> Datos vigentes por periodicidad quinquenal. La fuente de información tiene periodicidad trimestral, pero para hacer manejable la cantidad de información, se determinó tomarla de manera quinquenal.
A39: 31 | B39: Económica | C39: Población ocupada según sexo | D39: Porcentaje estatal de mujeres ocupadas | E39: =[1]Económica!E12 -> Porcentaje de mujeres ocupadas, por entidad federativa. | F39: =[1]Económica!F12 -> 2005, 2010, 2015 y 2020. | G39: =[1]Económica!G12 -> Estatal | H39: =[1]Económica!H12 -> Distribución porcentual de mujeres de 15 y más años de edad ocupadas, es decir, que durante la semana de referencia presentaron una de las siguientes situaciones: trabajaron al menos una hora o un día para producir bienes y servicios a cambio de una remuneración monetaria o en especie; tenían empleo pero no trabajaron por alguna causa sin dejar de percibir su ingreso; tenían empleo pero no trabajaron por alguna causa, dejando de percibir su ingreso pero con retorno asegurado a su trabajo en menos de 4 semanas; no tenían empleo, pero iniciarán con seguridad uno en 4 semanas o menos; trabajaron al menos una hora o un día en la semana de referencia, sin recibir pago alguno (ni monetario ni en especie) en un negocio propiedad de un familiar o no familiar, en la fecha de referencia al levantamiento por entidad federativa. | I39: =[1]Económica!I12 -> Por sexo. | J39: =[1]Económica!J12 -> Promedio anual de la población ocupada según sexo (mujeres/hombres), entre el promedio anual de la población ocupada total, multiplicado por 100. | K39: =[1]Económica!K12 -> Cálculos por el Colegio de Geografía (UNAM) y de la CNDH a partir de la información del Instituto Nacional de Estadística y Geografía (INEGI) | L39: =[1]Económica!L12 -> Porcentaje | ... P39: =[1]Económica!P12 -> 1. Para el 2020, el promedio no integra el 2o trimestre por suspensión de la ENOE por contigencia sanitaria de COVID-19. 2. La fuente de información tiene periodicidad trimestral, pero para hacer manejable la cantidad de información, se determinó tomarla de manera quinquenal. | Q39: =[1]Económica!AE12 -> Datos vigentes por periodicidad quinquenal. La fuente de información tiene periodicidad trimestral, pero para hacer manejable la cantidad de información, se determinó tomarla de manera quinquenal.
A40: 32 | B40: Económica | C40: Población ocupada según sexo | D40: Porcentaje estatal de hombres ocupados | E40: =[1]Económica!E13 -> Porcentaje de hombres ocupados, por entidad federativa. | F40: =[1]Económica!F13 -> 2005, 2010, 2015 y 2020. | G40: =[1]Económica!G13 -> Estatal | H40: =[1]Económica!H13 -> Distribución porcentual de hombres de 15 y más años de edad ocupados, es decir, que durante la semana de referencia presentaron una de las siguientes situaciones: trabajaron al menos una hora o un día para producir bienes y servicios a cambio de una remuneración monetaria o en especie; tenían empleo pero no trabajaron por alguna causa sin dejar de percibir su ingreso; tenían empleo pero no trabajaron por alguna causa, dejando de percibir su ingreso pero con retorno asegurado a su trabajo en menos de 4 semanas; no tenían empleo, pero iniciarán con seguridad uno en 4 semanas o menos; trabajaron al menos una hora o un día en la semana de referencia, sin recibir pago alguno (ni monetario ni en especie) en un negocio propiedad de un familiar o no familiar, en la fecha de referencia al levantamiento por entidad federativa. | I40: =[1]Económica!I13 -> Por sexo. | J40: =[1]Económica!J13 -> Promedio anual de la población ocupada según sexo (mujeres/hombres), entre el promedio anual de la población ocupada total, multiplicado por 100. | K40: =[1]Económica!K13 -> Cálculos por el Colegio de Geografía (UNAM) y de la CNDH a partir de la información del Instituto Nacional de Estadística y Geografía (INEGI) | L40: =[1]Económica!L13 -> Porcentaje | ... P40: =[1]Económica!P13 -> 1. Para el 2020, el promedio no integra el 2o trimestre por suspensión de la ENOE por contigencia sanitaria de COVID-19. 2. La fuente de información tiene periodicidad trimestral, pero para hacer manejable la cantidad de información, se determinó tomarla de manera quinquenal. | Q40: =[1]Económica!AE13 -> Datos vigentes por periodicidad quinquenal. La fuente de información tiene periodicidad trimestral, pero para hacer manejable la cantidad de información, se determinó tomarla de manera quinquenal.
A41: 33 | B41: Económica | C41: Población ocupada por nivel de ingreso según sexo | D41: Porcentaje estatal de la población que recibe hasta un salario mínimo | E41: =[1]Económica!E14 -> Porcentaje de población que recibe hasta un salario mínimo, por entidad federativa. | F41: =[1]Económica!F14 -> 2005, 2010, 2015 y 2020. | G41: =[1]Económica!G14 -> Estatal | H41: =[1]Económica!H14 -> Distribución porcentual de la población total en función del nivel de ingreso según el número de salarios que recibe, en la fecha de referencia al levantamiento por entidad federativa. | I41: =[1]Económica!I14 -> Por nivel de ingreso. | J41: =[1]Económica!J14 -> Promedio anual de la población ocupada de 12 y más años de edad según sexo (mujeres/hombres), por rango salarial que reciben (Hasta un S.M.; más de 1 y hasta 2 S.M.; más de 2 hasta 3 S.M.; más de 3 hasta 5 S.M.; más de 5 S.M.), entre el promedio anua de la población ocupada total, multiplicado por 100. | K41: =[1]Económica!K14 -> Cálculos por el Colegio de Geografía (UNAM) y de la CNDH a partir de la información del Instituto Nacional de Estadística y Geografía (INEGI) | L41: =[1]Económica!L14 -> Porcentaje | ... P41: =[1]Económica!P14 -> 1. Para el 2020, el promedio no integra el 2o trimestre por suspensión de la ENOE por contigencia sanitaria de COVID-19. 2. La fuente de información tiene periodicidad trimestral, pero para hacer manejable la cantidad de información, se determinó tomarla de manera quinquenal. Abreviatura S.M.: salario mínimo. | Q41: =[1]Económica!AE14 -> Datos vigentes por periodicidad quinquenal. La fuente de información tiene periodicidad trimestral, pero para hacer manejable la cantidad de información, se determinó tomarla de manera quinquenal.
A42: 34 | B42: Económica | C42: Población ocupada por nivel de ingreso según sexo | D42: Porcentaje estatal de mujeres que reciben hasta un salario mínimo | E42: =[1]Económica!E15 -> Porcentaje de mujeres que su nivel de ingreso es hasta un salario mínimo, por entidad federativa. | F42: =[1]Económica!F15 -> 2005, 2010, 2015 y 2020. | G42: =[1]Económica!G15 -> Estatal | H42: =[1]Económica!H15 -> Distribución porcentual de mujeres en función del nivel de ingreso según el número de salarios que recibe, en la fecha de referencia al levantamiento por entidad federativa. | I42: =[1]Económica!I15 -> Por sexo y nivel de ingreso | J42: =[1]Económica!J15 -> Promedio anual de la población ocupada de 12 y más años de edad según sexo (mujeres/hombres), por rango salarial que reciben (Hasta un S.M.; más de 1 y hasta 2 S.M.; más de 2 hasta 3 S.M.; más de 3 hasta 5 S.M.; más de 5 S.M.), entre el promedio anua de la población ocupada total, multiplicado por 100. | K42: =[1]Económica!K15 -> Cálculos por el Colegio de Geografía (UNAM) y de la CNDH a partir de la información del Instituto Nacional de Estadística y Geografía (INEGI) | L42: =[1]Económica!L15 -> Porcentaje | ... P42: =[1]Económica!P15 -> 1. Para el 2020, el promedio no integra el 2o trimestre por suspensión de la ENOE por contigencia sanitaria de COVID-19. 2. La fuente de información tiene periodicidad trimestral, pero para hacer manejable la cantidad de información, se determinó tomarla de manera quinquenal. Abreviatura S.M.: salario mínimo. | Q42: =[1]Económica!AE15 -> Datos vigentes por periodicidad quinquenal. La fuente de información tiene periodicidad trimestral, pero para hacer manejable la cantidad de información, se determinó tomarla de manera quinquenal.
... A77: 69 | B77: Económica | C77: Total de hogares según sexo de jefatura de familia | D77: Porcentaje estatal de hogares con jefatura de familia masculina | E77: =[1]Económica!E50 -> Porcentaje de hogares con jefatura de familia masculina, por entidad federativa. | F77: =[1]Económica!F50 -> 2005, 2010, 2015 y 2020 | G77: =[1]Económica!G50 -> Estatal | H77: =[1]Económica!H50 -> Distribución porcentual de viviendas particulares habitadas con jefatura de hogar masculina, en la fecha de referencia al levantamiento por entidad federativa. | I77: =[1]Económica!I50 -> Por sexo | J77: =[1]Económica!J50 -> Suma de las viviendas particulares habitadas según sexo de jefatura de hogar (mujeres/hombres), entre el total de viviendas particulares habitadas, multiplicado por 100. | K77: =[1]Económica!K50 -> Cálculos por el Colegio de Geografía (UNAM) y de la CNDH a partir de la información del Instituto Nacional de Estadística y Geografía (INEGI) | L77: =[1]Económica!L50 -> Porcentaje | ... P77: =[1]Económica!P50 -> 0 | Q77: =[1]Económica!AE50 -> Datos vigentes por periodicidad quinquenal.
A78: 70 | B78: Económica | C78: Población en situación de pobreza según sexo | D78: Porcentaje estatal de la población en situación de pobreza | E78: =[1]Económica!E52 -> Porcentaje de la población en situación de pobreza, por entidad federativa. | F78: =[1]Económica!F52 -> 2008, 2010, 2012, 2014, 2016, 2018, 2020 y 2022. | G78: =[1]Económica!G52 -> Estatal | H78: =[1]Económica!H52 -> Distribución porcentual de la población que tiene al menos una carencia social (en los seis indicadores de rezago educativo, acceso a servicios de salud, acceso a la seguridad social, calidad y espacios de la vivienda, servicios básicos en la vivienda y acceso a la alimentación) y su ingreso es insuficiente para adquirir los bienes y servicios que requiere para satisfacer sus necesidades alimentarias y no alimentarias, en la fecha de referencia al levantamiento por entidad federativa. | I78: =[1]Económica!I52 -> Por nivel de pobreza. | J78: =[1]Económica!J52 -> Distribución porcentual de la población en situación de pobreza, es decir, cuando tiene al menos una carencia social (en los seis indicadores de rezago educativo, acceso a servicios de salud, acceso a la seguridad social, calidad y espacios de la vivienda, servicios básicos en la vivienda y acceso a la alimentación) y su ingreso es insuficiente para adquirir los bienes y servicios que requiere para satisfacer sus necesidades alimentarias y no alimentarias, entre el total de la población, multiplicado por 100. | K78: =[1]Económica!K52 -> Cálculos por el Colegio de Geografía (UNAM) y de la CNDH a partir de la información de las estimaciones del Consejo Nacional de Evaluación de la Política de Desarrollo Social (CONEVAL), con base en el Módulo de Condiciones Socioeconómicas (MCS) de la Encuesta Nacional de Ingresos y Gastos de los Hogares (ENIGH) y el Modelo Estadístico 2016 para la continuidad del MCS-ENIGH. | L78: =[1]Económica!L52 -> Porcentaje | ... P78: =[1]Económica!P52 -> Con corte al segundo trimestre de 2024, la fuente oficial de información no cuenta con actualización de datos. | Q78: =[1]Económica!AE52 -> Datos vigentes por periodicidad bianual, sin embargo, la fuente oficial de información no cuenta con actualización de datos.
A79: 71 | B79: Económica | C79: Población en situación de pobreza según sexo | D79: Porcentaje estatal de mujeres en situación de pobreza | E79: =[1]Económica!E53 -> Porcentaje de mujeres en situación de pobreza, por entidad federativa. | F79: =[1]Económica!F53 -> 2008, 2010, 2012, 2014, 2016, 2018, 2020 y 2022. | G79: =[1]Económica!G53 -> Estatal | H79: =[1]Económica!H53 -> Distribución porcentual de mujeres que tiene al menos una carencia social (en los seis indicadores de rezago educativo, acceso a servicios de salud, acceso a la seguridad social, calidad y espacios de la vivienda, servicios básicos en la vivienda y acceso a la alimentación) y su ingreso es insuficiente para adquirir los bienes y servicios que requiere para satisfacer sus necesidades alimentarias y no alimentarias, en la fecha de referencia al levantamiento por entidad federativa. | I79: =[1]Económica!I53 -> Por sexo y nivel de pobreza. | J79: =[1]Económica!J53 -> Distribución porcentual de la población según sexo (mujeres/hombres) en situación de pobreza, es decir, cuando tiene al menos una carencia social (en los seis indicadores de rezago educativo, acceso a servicios de salud, acceso a la seguridad social, calidad y espacios de la vivienda, servicios básicos en la vivienda y acceso a la alimentación) y su ingreso es insuficiente para adquirir los bienes y servicios que requiere para satisfacer sus necesidades alimentarias y no alimentarias, entre el total de la población según sexo (mujeres/hombres), multiplicado por 100. | K79: =[1]Económica!K53 -> Cálculos por el Colegio de Geografía (UNAM) y de la CNDH a partir de la información de las estimaciones del Consejo Nacional de Evaluación de la Política de Desarrollo Social (CONEVAL), con base en el Módulo de Condiciones Socioeconómicas (MCS) de la Encuesta Nacional de Ingresos y Gastos de los Hogares (ENIGH) y el Modelo Estadístico 2016 para la continuidad del MCS-ENIGH. | L79: =[1]Económica!L53 -> Porcentaje | ... P79: =[1]Económica!P53 -> Con corte al segundo trimestre de 2024, la fuente oficial de información no cuenta con actualización de datos. | Q79: =[1]Económica!AE53 -> Datos vigentes por periodicidad bianual, sin embargo, la fuente oficial de información no cuenta con actualización de datos.
A80: 72 | B80: Económica | C80: Población en situación de pobreza según sexo | D80: Porcentaje estatal de hombres en situación de pobreza | E80: =[1]Económica!E54 -> Porcentaje de hombres en situación de pobreza, por entidad federativa. | F80: =[1]Económica!F54 -> 2008, 2010, 2012, 2014, 2016, 2018, 2020 y 2022. | G80: =[1]Económica!G54 -> Estatal | H80: =[1]Económica!H54 -> Distribución porcentual de hombres que tiene al menos una carencia social (en los seis indicadores de rezago educativo, acceso a servicios de salud, acceso a la seguridad social, calidad y espacios de la vivienda, servicios básicos en la vivienda y acceso a la alimentación) y su ingreso es insuficiente para adquirir los bienes y servicios que requiere para satisfacer sus necesidades alimentarias y no alimentarias, en la fecha de referencia al levantamiento por entidad federativa. | I80: =[1]Económica!I54 -> Por sexo y nivel de pobreza. | J80: =[1]Económica!J54 -> Distribución porcentual de la población según sexo (mujeres/hombres) en situación de pobreza, es decir, cuando tiene al menos una carencia social (en los seis indicadores de rezago educativo, acceso a servicios de salud, acceso a la seguridad social, calidad y espacios de la vivienda, servicios básicos en la vivienda y acceso a la alimentación) y su ingreso es insuficiente para adquirir los bienes y servicios que requiere para satisfacer sus necesidades alimentarias y no alimentarias, entre el total de la población según sexo (mujeres/hombres), multiplicado por 100. | K80: =[1]Económica!K54 -> Cálculos por el Colegio de Geografía (UNAM) y de la CNDH a partir de la información de las estimaciones del Consejo Nacional de Evaluación de la Política de Desarrollo Social (CONEVAL), con base en el Módulo de Condiciones Socioeconómicas (MCS) de la Encuesta Nacional de Ingresos y Gastos de los Hogares (ENIGH) y el Modelo Estadístico 2016 para la continuidad del MCS-ENIGH. | L80: =[1]Económica!L54 -> Porcentaje | ... P80: =[1]Económica!P54 -> Con corte al segundo trimestre de 2024, la fuente oficial de información no cuenta con actualización de datos. | Q80: =[1]Económica!AE54 -> Datos vigentes por periodicidad bianual, sin embargo, la fuente oficial de información no cuenta con actualización de datos.
A81: 73 | B81: Económica | C81: Población en situación de pobreza según sexo | D81: Porcentaje estatal de la población en situación de pobreza moderada | E81: =[1]Económica!E55 -> Porcentaje de la población en situación de pobreza moderada, por entidad federativa. | F81: =[1]Económica!F55 -> 2008, 2010, 2012, 2014, 2016, 2018, 2020 y 2022. | G81: =[1]Económica!G55 -> Estatal | H81: =[1]Económica!H55 -> Distribución porcentual de la población que, de acuerdo a CONEVAL, siendo pobre, no es pobre extrema (la incidencia de pobreza moderada se obtiene al calcular la diferencia entre la incidencia de la población en pobreza menos la de la población en pobreza extrema), en la fecha de referencia al levantamiento por entidad federativa. | I81: =[1]Económica!I55 -> Por nivel de pobreza. | J81: =[1]Económica!J55 -> Distribución porcentual de la población en situación de pobreza moderada, entre el total de la población en situación de pobreza, multiplicado por 100. | K81: =[1]Económica!K55 -> Cálculos por el Colegio de Geografía (UNAM) y de la CNDH a partir de la información de las estimaciones del Consejo Nacional de Evaluación de la Política de Desarrollo Social (CONEVAL), con base en el Módulo de Condiciones Socioeconómicas (MCS) de la Encuesta Nacional de Ingresos y Gastos de los Hogares (ENIGH) y el Modelo Estadístico 2016 para la continuidad del MCS-ENIGH. | L81: =[1]Económica!L55 -> Porcentaje | ... P81: =[1]Económica!P55 -> Con corte al segundo trimestre de 2024, la fuente oficial de información no cuenta con actualización de datos. | Q81: =[1]Económica!AE55 -> Datos vigentes por periodicidad bianual, sin embargo, la fuente oficial de información no cuenta con actualización de datos.
A82: 74 | B82: Económica | C82: Población en situación de pobreza según sexo | D82: Porcentaje estatal de mujeres en situación de pobreza moderada | E82: =[1]Económica!E56 -> Porcentaje de mujeres en situación de pobreza moderada, por entidad federativa. | F82: =[1]Económica!F56 -> 2008, 2010, 2012, 2014, 2016, 2018, 2020 y 2022. | G82: =[1]Económica!G56 -> Estatal | H82: =[1]Económica!H56 -> Distribución porcentual de mujeres que, de acuerdo a CONEVAL, siendo pobre, no es pobre extrema (la incidencia de pobreza moderada se obtiene al calcular la diferencia entre la incidencia de la población en pobreza menos la de la población en pobreza extrema), en la fecha de referencia al levantamiento por entidad federativa. | I82: =[1]Económica!I56 -> Por sexo y nivel de pobreza. | J82: =[1]Económica!J56 -> Distribución porcentual de la población según sexo (mujeres/hombres) en situación de pobreza moderada, entre el total de la población en situación de pobreza según sexo (mujeres/hombres), multiplicado por 100. | K82: =[1]Económica!K56 -> Cálculos por el Colegio de Geografía (UNAM) y de la CNDH a partir de la información de las estimaciones del Consejo Nacional de Evaluación de la Política de Desarrollo Social (CONEVAL), con base en el Módulo de Condiciones Socioeconómicas (MCS) de la Encuesta Nacional de Ingresos y Gastos de los Hogares (ENIGH) y el Modelo Estadístico 2016 para la continuidad del MCS-ENIGH. | L82: =[1]Económica!L56 -> Porcentaje | ... P82: =[1]Económica!P56 -> Con corte al segundo trimestre de 2024, la fuente oficial de información no cuenta con actualización de datos. | Q82: =[1]Económica!AE56 -> Datos vigentes por periodicidad bianual, sin embargo, la fuente oficial de información no cuenta con actualización de datos.
A83: 75 | B83: Económica | C83: Población en situación de pobreza según sexo | D83: Porcentaje estatal de hombres en situación de pobreza moderada | E83: =[1]Económica!E57 -> Porcentaje de hombres en situación de pobreza moderada, por entidad federativa. | F83: =[1]Económica!F57 -> 2008, 2010, 2012, 2014, 2016, 2018, 2020 y 2022. | G83: =[1]Económica!G57 -> Estatal | H83: =[1]Económica!H57 -> Distribución porcentual de hombres que, de acuerdo a CONEVAL, siendo pobre, no es pobre extrema (la incidencia de pobreza moderada se obtiene al calcular la diferencia entre la incidencia de la población en pobreza menos la de la población en pobreza extrema), en la fecha de referencia al levantamiento por entidad federativa. | I83: =[1]Económica!I57 -> Por sexo y nivel de pobreza. | J83: =[1]Económica!J57 -> Distribución porcentual de la población según sexo (mujeres/hombres) en situación de pobreza moderada, entre el total de la población en situación de pobreza según sexo (mujeres/hombres), multiplicado por 100. | K83: =[1]Económica!K57 -> Cálculos por el Colegio de Geografía (UNAM) y de la CNDH a partir de la información de las estimaciones del Consejo Nacional de Evaluación de la Política de Desarrollo Social (CONEVAL), con base en el Módulo de Condiciones Socioeconómicas (MCS) de la Encuesta Nacional de Ingresos y Gastos de los Hogares (ENIGH) y el Modelo Estadístico 2016 para la continuidad del MCS-ENIGH. | L83: =[1]Económica!L57 -> Porcentaje | ... P83: =[1]Económica!P57 -> Con corte al segundo trimestre de 2024, la fuente oficial de información no cuenta con actualización de datos. | Q83: =[1]Económica!AE57 -> Datos vigentes por periodicidad bianual, sin embargo, la fuente oficial de información no cuenta con actualización de datos.
A84: 76 | B84: Económica | C84: Población en situación de pobreza según sexo | D84: Porcentaje estatal de la población en situación de pobreza extrema | E84: =[1]Económica!E58 -> Porcentaje de la población en situación de pobreza extrema, por entidad federativa. | F84: =[1]Económica!F58 -> 2008, 2010, 2012, 2014, 2016, 2018, 2020 y 2022. | G84: =[1]Económica!G58 -> Estatal | H84: =[1]Económica!H58 -> Distribución porcentual de la población que tiene tres o más carencias, de seis posibles, dentro del Índice de Privación Social y que, además, se encuentra por debajo de la línea de bienestar mínimo (las personas en esta situación disponen de un ingreso tan bajo que, aun si lo dedicase por completo a la adquisición de alimentos, no podría adquirir los nutrientes necesarios para tener una vida sana), en la fecha de referencia al levantamiento por entidad federativa. | I84: =[1]Económica!I58 -> Por nivel de pobreza. | J84: =[1]Económica!J58 -> Distribución porcentual de la población en situación de pobreza extrema, es decir, que tiene tres o más carencias, de seis posibles, dentro del Índice de Privación Social y que, además, se encuentra por debajo de la línea de bienestar mínimo (las personas en esta situación disponen de un ingreso tan bajo que, aun si lo dedicase por completo a la adquisición de alimentos, no podría adquirir los nutrientes necesarios para tener una vida sana), entre el total de la población en situación de pobreza, multiplicado por 100. | K84: =[1]Económica!K58 -> Cálculos por el Colegio de Geografía (UNAM) y de la CNDH a partir de la información de las estimaciones del Consejo Nacional de Evaluación de la Política de Desarrollo Social (CONEVAL), con base en el Módulo de Condiciones Socioeconómicas (MCS) de la Encuesta Nacional de Ingresos y Gastos de los Hogares (ENIGH) y el Modelo Estadístico 2016 para la continuidad del MCS-ENIGH. | L84: =[1]Económica!L58 -> Porcentaje | ... P84: =[1]Económica!P58 -> Con corte al segundo trimestre de 2024, la fuente oficial de información no cuenta con actualización de datos. | Q84: =[1]Económica!AE58 -> Datos vigentes por periodicidad bianual, sin embargo, la fuente oficial de información no cuenta con actualización de datos.
A85: 77 | B85: Económica | C85: Población en situación de pobreza según sexo | D85: Porcentaje estatal de mujeres en situación de pobreza extrema | E85: =[1]Económica!E59 -> Porcentaje de mujeres en situación de pobreza extrema, por entidad federativa. | F85: =[1]Económica!F59 -> 2008, 2010, 2012, 2014, 2016, 2018, 2020 y 2022. | G85: =[1]Económica!G59 -> Estatal | H85: =[1]Económica!H59 -> Distribución porcentual de mujeres que tiene tres o más carencias, de seis posibles, dentro del Índice de Privación Social y que, además, se encuentra por debajo de la línea de bienestar mínimo (las personas en esta situación disponen de un ingreso tan bajo que, aun si lo dedicase por completo a la adquisición de alimentos, no podría adquirir los nutrientes necesarios para tener una vida sana), en la fecha de referencia al levantamiento por entidad federativa. | I85: =[1]Económica!I59 -> Por sexo y nivel de pobreza. | J85: =[1]Económica!J59 -> Distribución porcentual de la población según sexo (mujeres/hombres) en situación de pobreza extrema, es decir, que tiene tres o más carencias, de seis posibles, dentro del Índice de Privación Social y que, además, se encuentra por debajo de la línea de bienestar mínimo (las personas en esta situación disponen de un ingreso tan bajo que, aun si lo dedicase por completo a la adquisición de alimentos, no podría adquirir los nutrientes necesarios para tener una vida sana), entre el total de la población en situación de pobreza según sexo (mujeres/hombres), multiplicado por 100. | K85: =[1]Económica!K59 -> Cálculos por el Colegio de Geografía (UNAM) y de la CNDH a partir de la información de las estimaciones del Consejo Nacional de Evaluación de la Política de Desarrollo Social (CONEVAL), con base en el Módulo de Condiciones Socioeconómicas (MCS) de la Encuesta Nacional de Ingresos y Gastos de los Hogares (ENIGH) y el Modelo Estadístico 2016 para la continuidad del MCS-ENIGH. | L85: =[1]Económica!L59 -> Porcentaje | ... P85: =[1]Económica!P59 -> Con corte al segundo trimestre de 2024, la fuente oficial de información no cuenta con actualización de datos. | Q85: =[1]Económica!AE59 -> Datos vigentes por periodicidad bianual, sin embargo, la fuente oficial de información no cuenta con actualización de datos.
A86: 78 | B86: Económica | C86: Población en situación de pobreza según sexo | D86: Porcentaje estatal de hombres en situación de pobreza extrema | E86: =[1]Económica!E60 -> Porcentaje de hombres en situación de pobreza extrema, por entidad federativa. | F86: =[1]Económica!F60 -> 2008, 2010, 2012, 2014, 2016, 2018, 2020 y 2022. | G86: =[1]Económica!G60 -> Estatal | H86: =[1]Económica!H60 -> Distribución porcentual de hombres que tiene tres o más carencias, de seis posibles, dentro del Índice de Privación Social y que, además, se encuentra por debajo de la línea de bienestar mínimo (las personas en esta situación disponen de un ingreso tan bajo que, aun si lo dedicase por completo a la adquisición de alimentos, no podría adquirir los nutrientes necesarios para tener una vida sana), en la fecha de referencia al levantamiento por entidad federativa. | I86: =[1]Económica!I60 -> Por sexo y nivel de pobreza. | J86: =[1]Económica!J60 -> Distribución porcentual de la población según sexo (mujeres/hombres) en situación de pobreza extrema, es decir, que tiene tres o más carencias, de seis posibles, dentro del Índice de Privación Social y que, además, se encuentra por debajo de la línea de bienestar mínimo (las personas en esta situación disponen de un ingreso tan bajo que, aun si lo dedicase por completo a la adquisición de alimentos, no podría adquirir los nutrientes necesarios para tener una vida sana), entre el total de la población en situación de pobreza según sexo (mujeres/hombres), multiplicado por 100. | K86: =[1]Económica!K60 -> Cálculos por el Colegio de Geografía (UNAM) y de la CNDH a partir de la información de las estimaciones del Consejo Nacional de Evaluación de la Política de Desarrollo Social (CONEVAL), con base en el Módulo de Condiciones Socioeconómicas (MCS) de la Encuesta Nacional de Ingresos y Gastos de los Hogares (ENIGH) y el Modelo Estadístico 2016 para la continuidad del MCS-ENIGH. | L86: =[1]Económica!L60 -> Porcentaje | ... P86: =[1]Económica!P60 -> Con corte al segundo trimestre de 2024, la fuente oficial de información no cuenta con actualización de datos. | Q86: =[1]Económica!AE60 -> Datos vigentes por periodicidad bianual, sin embargo, la fuente oficial de información no cuenta con actualización de datos.
A87: 79 | B87: Económica | C87: Población vulnerable según sexo | D87: Porcentaje estatal de la población vulnerable por carencias sociales | E87: =[1]Económica!E61 -> Porcentaje de la población vulnerable por carencias sociales, por entidad federativa. | F87: =[1]Económica!F61 -> 2008, 2010, 2012, 2014, 2016, 2018, 2020 y 2022. | G87: =[1]Económica!G61 -> Estatal | H87: =[1]Económica!H61 -> Distribución porcentual de la población que presentan una o más carencias sociales, pero cuyo ingreso es superior a la línea de bienestar, en la fecha de referencia al levantamiento por entidad federativa. | I87: =[1]Económica!I61 -> Por tipo de situación de vulnerabilidad. | J87: =[1]Económica!J61 -> Suma de la población vulnerable por carencias sociales según entidad federativa, es decir, que presenta una o más carencias sociales, pero cuyo ingreso es superior a la línea de bienestar, entre el total de la población vulnerable por carencias sociales, multiplicado por 100. | K87: =[1]Económica!K61 -> Cálculos por el Colegio de Geografía (UNAM) y de la CNDH a partir de la información de las estimaciones del Consejo Nacional de Evaluación de la Política de Desarrollo Social (CONEVAL), con base en el Módulo de Condiciones Socioeconómicas (MCS) de la Encuesta Nacional de Ingresos y Gastos de los Hogares (ENIGH) y el Modelo Estadístico 2016 para la continuidad del MCS-ENIGH. | L87: =[1]Económica!L61 -> Porcentaje | ... P87: =[1]Económica!P61 -> 1. Por carencias sociales se entiende: rezago educativo, acceso a los servicios de salud, acceso a la seguridad social, calidad y espacios de la vivienda, acceso a los servicios básicos de la vivienda, y acceso a la alimentación. 2. Con corte al segundo trimestre de 2024, la fuente oficial de información no cuenta con actualización de datos. | Q87: =[1]Económica!AE61 -> Datos vigentes por periodicidad bianual, sin embargo, la fuente oficial de información no cuenta con actualización de datos.
A88: 80 | B88: Económica | C88: Población vulnerable según sexo | D88: Porcentaje estatal de mujeres vulnerables por carencias sociales | E88: =[1]Económica!E62 -> Porcentaje de mujeres vulnerable por carencias sociales, por entidad federativa. | F88: =[1]Económica!F62 -> 2008, 2010, 2012, 2014, 2016, 2018, 2020 y 2022. | G88: =[1]Económica!G62 -> Estatal | H88: =[1]Económica!H62 -> Distribución porcentual de mujeres que presentan una o más carencias sociales, pero cuyo ingreso es superior a la línea de bienestar, en la fecha de referencia al levantamiento por entidad federativa. | I88: =[1]Económica!I62 -> Por tipo de situación de vulnerabilidad y sexo. | J88: =[1]Económica!J62 -> Suma de la población vulnerable según sexo (mujeres/hombres) por carencias sociales según entidad federativa, es decir, que presenta una o más carencias sociales, pero cuyo ingreso es superior a la línea de bienestar, entre el total de la población vulnerable por carencias sociales según sexo (mujeres/hombres), multiplicado por 100. | K88: =[1]Económica!K62 -> Cálculos por el Colegio de Geografía (UNAM) y de la CNDH a partir de la información de las estimaciones del Consejo Nacional de Evaluación de la Política de Desarrollo Social (CONEVAL), con base en el Módulo de Condiciones Socioeconómicas (MCS) de la Encuesta Nacional de Ingresos y Gastos de los Hogares (ENIGH) y el Modelo Estadístico 2016 para la continuidad del MCS-ENIGH. | L88: =[1]Económica!L62 -> Porcentaje | ... P88: =[1]Económica!P62 -> 1. Por carencias sociales se entiende: rezago educativo, acceso a los servicios de salud, acceso a la seguridad social, calidad y espacios de la vivienda, acceso a los servicios básicos de la vivienda, y acceso a la alimentación. 2. Con corte al segundo trimestre de 2024, la fuente oficial de información no cuenta con actualización de datos. | Q88: =[1]Económica!AE62 -> Datos vigentes por periodicidad bianual, sin embargo, la fuente oficial de información no cuenta con actualización de datos.
A89: 81 | B89: Económica | C89: Población vulnerable según sexo | D89: Porcentaje estatal de hombres vulnerables por carencias sociales | E89: =[1]Económica!E63 -> Porcentaje de hombres vulnerable por carencias sociales, por entidad federativa. | F89: =[1]Económica!F63 -> 2008, 2010, 2012, 2014, 2016, 2018, 2020 y 2022. | G89: =[1]Económica!G63 -> Estatal | H89: =[1]Económica!H63 -> Distribución porcentual de hombres que presentan una o más carencias sociales, pero cuyo ingreso es superior a la línea de bienestar, en la fecha de referencia al levantamiento por entidad federativa. | I89: =[1]Económica!I63 -> Por tipo de situación de vulnerabilidad y sexo. | J89: =[1]Económica!J63 -> Suma de la población vulnerable según sexo (mujeres/hombres) por carencias sociales según entidad federativa, es decir, que presenta una o más carencias sociales, pero cuyo ingreso es superior a la línea de bienestar, entre el total de la población vulnerable por carencias sociales según sexo (mujeres/hombres), multiplicado por 100. | K89: =[1]Económica!K63 -> Cálculos por el Colegio de Geografía (UNAM) y de la CNDH a partir de la información de las estimaciones del Consejo Nacional de Evaluación de la Política de Desarrollo Social (CONEVAL), con base en el Módulo de Condiciones Socioeconómicas (MCS) de la Encuesta Nacional de Ingresos y Gastos de los Hogares (ENIGH) y el Modelo Estadístico 2016 para la continuidad del MCS-ENIGH. | L89: =[1]Económica!L63 -> Porcentaje | ... P89: =[1]Económica!P63 -> 1. Por carencias sociales se entiende: rezago educativo, acceso a los servicios de salud, acceso a la seguridad social, calidad y espacios de la vivienda, acceso a los servicios básicos de la vivienda, y acceso a la alimentación. 2. Con corte al segundo trimestre de 2024, la fuente oficial de información no cuenta con actualización de datos. | Q89: =[1]Económica!AE63 -> Datos vigentes por periodicidad bianual, sin embargo, la fuente oficial de información no cuenta con actualización de datos.
... A102: 94 | B102: Económica | C102: Presupuesto para los Mecanismos para el Adelanto de las Mujeres | D102: Presupuesto asignado a los Consejos (MAM) | E102: =[1]Económica!E76 -> Presupuesto asignado a los Consejos de las Mujeres (u homólogo en nombre), por entidad federativa. | F102: =[1]Económica!F76 -> 2011-2024 | G102: =[1]Económica!G76 -> Estatal | H102: =[1]Económica!H76 -> Total de los presupuestos destinados para uso del Nivel 1 (bajo) de los MAM que promueven la igualdad, el bienestar social y de salud de las mujeres,definidos desde la evaluación de la perspectiva de género en los programas presupuestarios, por entidad federativa. | I102: =[1]Económica!I76 -> Por nivel jerárquico. | J102: =[1]Económica!J76 -> Suma de presupuestos asignados a los Consejos que promueven la igualdad, el bienestar social y de salud de las mujeres,definidos desde la evaluación de la perspectiva de género en los programas presupuestarios, en el año de referencia, por entidad federativa. | K102: =[1]Económica!K76 -> Cálculos por el Colegio de Geografía (UNAM) a partir de la información del Instituto Nacional para el Federalismo y el Desarrollo Municipal (INAFED) | L102: =[1]Económica!L76 -> Pesos mexicanos | ... P102: =[1]Económica!P76 -> 0 | Q102: =[1]Económica!AE76 -> Datos vigentes con actualización a 2024.
A103: 95 | B103: Violencia | C103: Con solicitud de Alerta de Violencia de Género contra las Mujeres | D103: Con solicitud de declaratoria de AVGM por Violencia Feminicida | E103: =[1]Violencia!E4 -> Con solicitud de declaratoria de Alerta de Violencia de Género contra las Mujeres por Violencia Feminicida, por entidad federativa. | F103: =[1]Violencia!F4 -> A marzo 2022 | G103: =[1]Violencia!G4 -> Estatal | H103: =[1]Violencia!H4 -> Situación actual de los procedimientos de Alerta de Violencia de Género contra las Mujeres (AVGM) con solicitud de declaratoria de AVGM por tipo (Violencia Feminicida, Agravio Comparado y Desaparición), por entidad federativa. | I103: =[1]Violencia!I4 -> Por AVGM solicitada y tipo de AVGM. | J103: =[1]Violencia!J4 -> Suma del número total de entidades federativas con AVGM solicitada, por tipo de AVGM (Violencia Feminicida, Agravio Comparado y Desaparición), por entidad federativa. | K103: =[1]Violencia!K4 -> Comisión Nacional de los Derechos Humanos (CNDH) con información de la CNDH y de la Comisión Nacional para Prevenir y Erradicar la Violencia contra las Mujeres (Conavim). | L103: =[1]Violencia!L4 -> Fase del procedimiento de Alerta de Violencia de Género. | ... O103: =[1]Violencia!O4 -> Ley General de Acceso de las Mujeres a una Vida Libre de Violencia: Capítulo V. Reglamento de la Ley General de Acceso de las Mujeres a una Vida Libre de Violencia: Título Tercero, Capítulo I. | Q103: =[1]Violencia!AE4 -> Datos vigentes
A104: 96 | B104: Violencia | C104: Con solicitud de Alerta de Violencia de Género contra las Mujeres | D104: Con solicitud de declaratoria de AVGM por Agravio Comparado | E104: =[1]Violencia!E5 -> Con solicitud de declaratoria de Alerta de Violencia de Género contra las Mujeres por Agravio Comparado, por entidad federativa. | F104: =[1]Violencia!F5 -> A marzo 2022 | G104: =[1]Violencia!G5 -> Estatal | H104: =[1]Violencia!H5 -> Situación actual de los procedimientos de Alerta de Violencia de Género contra las Mujeres (AVGM) con solicitud de declaratoria de AVGM por tipo (Violencia Feminicida, Agravio Comparado y Desaparición), por entidad federativa. | I104: =[1]Violencia!I5 -> Por AVGM solicitada y tipo de AVGM. | J104: =[1]Violencia!J5 -> Suma del número total de entidades federativas con AVGM solicitada, por tipo de AVGM (Violencia Feminicida, Agravio Comparado y Desaparición), por entidad federativa. | K104: =[1]Violencia!K5 -> Comisión Nacional de los Derechos Humanos (CNDH) con información de la CNDH y de la Comisión Nacional para Prevenir y Erradicar la Violencia contra las Mujeres (Conavim). | L104: =[1]Violencia!L5 -> Fase del procedimiento de Alerta de Violencia de Género. | ... P104: =[1]Violencia!P5 -> 1. Fecha de corte: mayo 2022. Posterior a esa fecha, no se ha encontrado actualización en la fuente de información. 2. El sitio web de la CONAVIM, sobre Alertas de Violencia de Género contra las Mujeres (AVGM), señala que "*La información que contiene este blog y los links que la acompañan, se actualizan periódicamente.*", pero al no indicar una periodicidad específica, se considera su Periodicidad como No determinada. 3. Se señala con 1 cuando tiene solicitud, con 0 cuando no tiene solicitud. CDMX: Previo a la solicitud de declaratoria de AVGM por Violencia Feminicida de fecha 02/2020 realizada por la Fundación Nosotros por ti, la entidad tuvo una solicitud previa de AVGM con fecha 09/2017, la cual rechazada. Guanajuato: Previo a la solicitud de declaratoria de AVGM por Violencia Feminicida de fecha 03/2022 realizada por la CNDH, la entidad tuvo dos solicitudes de fechas 06/2009 y 03/2014, las cuales fueron rechazadas. Puebla: Previo a la solicitud de declaratoria de AVGM por Violencia Feminicida de fecha 03/2019 emitida por Comisión Estatal de Derechos Humanos, la entidad tuvo 5 solicitudes de fechas 09/03/2016, 30/03/2016, 20/10/2017, 23/10/2017, 17/11/2017 las cuales fueron acumuladas a la última solicitud de AVGM. Sonora: Tiene dos solicitudes de AVGM, la primera por VF y que fue declarada en 08/2021 y una segunda solicitud de fecha 11/2019 que en principio fue acumulada con la primera solicitud y posteriormente en 12/2020 se des acumuló quedando dos solicitudes de AVGM, una por VF (que ya está declarada) y otra por agravio comparado (que aún se encuentra en etapa de análisis de solicitud). Tlaxcala: Previo a la solicitud de declaratoria de AVGM por Violencia Feminicida de fecha 11/2019 emitida por la Organización de Mujeres de Tercer Milenio, la entidad tuvo una anterior de fecha 08/2016, la cual fue rechazada. | Q104: =[1]Violencia!AE5 -> Datos vigentes
A105: 97 | B105: Violencia | C105: Con solicitud de Alerta de Violencia de Género contra las Mujeres | D105: Con solicitud de declaratoria de AVGM por Desaparición | E105: =[1]Violencia!E6 -> Con solicitud de declaratoria de Alerta de Violencia de Género contra las Mujeres por Desaparición, por entidad federativa. | F105: =[1]Violencia!F6 -> A marzo 2022 | G105: =[1]Violencia!G6 -> Estatal | H105: =[1]Violencia!H6 -> Situación actual de los procedimientos de Alerta de Violencia de Género contra las Mujeres (AVGM) con solicitud de declaratoria de AVGM por tipo (Violencia Feminicida, Agravio Comparado y Desaparición), por entidad federativa. | I105: =[1]Violencia!I6 -> Por AVGM solicitada y tipo de AVGM. | J105: =[1]Violencia!J6 -> Suma del número total de entidades federativas con AVGM solicitada, por tipo de AVGM (Violencia Feminicida, Agravio Comparado y Desaparición), por entidad federativa. | K105: =[1]Violencia!K6 -> Comisión Nacional de los Derechos Humanos (CNDH) con información de la CNDH y de la Comisión Nacional para Prevenir y Erradicar la Violencia contra las Mujeres (Conavim). | L105: =[1]Violencia!L6 -> Fase del procedimiento de Alerta de Violencia de Género. | ... P105: =[1]Violencia!P6 -> 1. Fecha de corte: mayo 2022. Posterior a esa fecha, no se ha encontrado actualización en la fuente de información. 2. El sitio web de la CONAVIM, sobre Alertas de Violencia de Género contra las Mujeres (AVGM), señala que "*La información que contiene este blog y los links que la acompañan, se actualizan periódicamente.*", pero al no indicar una periodicidad específica, se considera su Periodicidad como No determinada. 3. Se señala con 1 cuando tiene solicitud, con 0 cuando no tiene solicitud. CDMX: Previo a la solicitud de declaratoria de AVGM por Violencia Feminicida de fecha 02/2020 realizada por la Fundación Nosotros por ti, la entidad tuvo una solicitud previa de AVGM con fecha 09/2017, la cual rechazada. Guanajuato: Previo a la solicitud de declaratoria de AVGM por Violencia Feminicida de fecha 03/2022 realizada por la CNDH, la entidad tuvo dos solicitudes de fechas 06/2009 y 03/2014, las cuales fueron rechazadas. Puebla: Previo a la solicitud de declaratoria de AVGM por Violencia Feminicida de fecha 03/2019 emitida por Comisión Estatal de Derechos Humanos, la entidad tuvo 5 solicitudes de fechas 09/03/2016, 30/03/2016, 20/10/2017, 23/10/2017, 17/11/2017 las cuales fueron acumuladas a la última solicitud de AVGM. Sonora: Tiene dos solicitudes de AVGM, la primera por VF y que fue declarada en 08/2021 y una segunda solicitud de fecha 11/2019 que en principio fue acumulada con la primera solicitud y posteriormente en 12/2020 se des acumuló quedando dos solicitudes de AVGM, una por VF (que ya está declarada) y otra por agravio comparado (que aún se encuentra en etapa de análisis de solicitud). Tlaxcala: Previo a la solicitud de declaratoria de AVGM por Violencia Feminicida de fecha 11/2019 emitida por la Organización de Mujeres de Tercer Milenio, la entidad tuvo una anterior de fecha 08/2016, la cual fue rechazada. | Q105: =[1]Violencia!AE6 -> Datos vigentes
A106: 98 | B106: Violencia | C106: Con solicitud de Alerta de Violencia de Género contra las Mujeres | D106: Se solicitó declaratoria de AVGM, pero no se declaró | E106: =[1]Violencia!E7 -> Se solicitó declaratoria de Alerta de Violencia de Género contra las Mujeres, pero no se declaró, por entidad federativa. | F106: =[1]Violencia!F7 -> A noviembre 2023 | G106: =[1]Violencia!G7 -> Estatal | H106: =[1]Violencia!H7 -> Situación actual de los procedimientos de Alerta de Violencia de Género contra las Mujeres (AVGM) solicitadas, pero no declaradas, por entidad federativa. | I106: =[1]Violencia!I7 -> Por AVGM declarada y tipo de AVGM. | J106: =[1]Violencia!J7 -> Suma del número total de entidades federativas con AVGM declarada, por tipo de AVGM (Violencia Feminicida, Agravio Comparado y Desaparición), por entidad federativa. | K106: =[1]Violencia!K7 -> Comisión Nacional de los Derechos Humanos (CNDH) con información de la CNDH y de la Comisión Nacional para Prevenir y Erradicar la Violencia contra las Mujeres (Conavim). | L106: =[1]Violencia!L7 -> Fase del procedimiento de Alerta de Violencia de Género. | ... P106: =[1]Violencia!P7 -> 1. Fecha de corte: noviembre 2023. 2. Se señala con 1 cuando tiene solicitud pero no se declaró. 3. El sitio web de la CONAVIM, sobre Alertas de Violencia de Género contra las Mujeres (AVGM), señala que "*La información que contiene este blog y los links que la acompañan, se actualizan periódicamente.*", pero al no indicar una periodicidad específica, se considera su Periodicidad como No determinada. CDMX: Previo a la solicitud de declaratoria de AVGM por Violencia Feminicida de fecha 02/2020 realizada por la Fundación Nosotros por ti, la entidad tuvo una solicitud previa de AVGM con fecha 09/2017, la cual rechazada. Guanajuato: Previo a la solicitud de declaratoria de AVGM por Violencia Feminicida de fecha 03/2022 realizada por la CNDH, la entidad tuvo dos solicitudes de fechas 06/2009 y 03/2014, las cuales fueron rechazadas. Puebla: Previo a la solicitud de declaratoria de AVGM por Violencia Feminicida de fecha 03/2019 emitida por Comisión Estatal de Derechos Humanos, la entidad tuvo 5 solicitudes de fechas 09/03/2016, 30/03/2016, 20/10/2017, 23/10/2017, 17/11/2017 las cuales fueron acumuladas a la última solicitud de AVGM. Sonora: Tiene dos solicitudes de AVGM, la primera por VF y que fue declarada en 08/2021 y una segunda solicitud de fecha 11/2019 que en principio fue acumulada con la primera solicitud y posteriormente en 12/2020 se des acumuló quedando dos solicitudes de AVGM, una por VF (que ya está declarada) y otra por agravio comparado (que aún se encuentra en etapa de análisis de solicitud). Tlaxcala: Previo a la solicitud de declaratoria de AVGM por Violencia Feminicida de fecha 11/2019 emitida por la Organización de Mujeres de Tercer Milenio, la entidad tuvo una anterior de fecha 08/2016, la cual fue rechazada. | Q106: =[1]Violencia!AE7 -> Datos vigentes
A107: 99 | B107: Violencia | C107: Con declaratoria de Alerta de Violencia de Género contra las Mujeres | D107: Con declaratoria de AVGM por Violencia Feminicida | E107: =[1]Violencia!E8 -> Con declaratoria de Alerta de Violencia de Género contra las Mujeres por Violencia Feminicida, por entidad federativa. | F107: =[1]Violencia!F8 -> A noviembre 2023 | G107: =[1]Violencia!G8 -> Estatal | H107: =[1]Violencia!H8 -> Situación actual de los procedimientos de Alerta de Violencia de Género contra las Mujeres (AVGM) declaradas a nivel nacional, por tipo de AVGM (Violencia Feminicida, Agravio Comparado y Desaparición), por entidad federativa. | I107: =[1]Violencia!I8 -> Por AVGM declarada y tipo de AVGM. | J107: =[1]Violencia!J8 -> Suma del número total de entidades federativas con AVGM declarada, por tipo de AVGM (Violencia Feminicida, Agravio Comparado y Desaparición), por entidad federativa. | K107: =[1]Violencia!K8 -> Comisión Nacional de los Derechos Humanos (CNDH) con información de la CNDH y de la Comisión Nacional para Prevenir y Erradicar la Violencia contra las Mujeres (Conavim). | L107: =[1]Violencia!L8 -> Fase del procedimiento de Alerta de Violencia de Género. | ... P107: =[1]Violencia!P8 -> 1. Fecha de corte: noviembre 2023. 2. El sitio web de la CONAVIM, sobre Alertas de Violencia de Género contra las Mujeres (AVGM), señala que "*La información que contiene este blog y los links que la acompañan, se actualizan periódicamente.*", pero al no indicar una periodicidad específica, se considera su Periodicidad como No determina. CDMX: Previo a la solicitud de declaratoria de AVGM por Violencia Feminicida de fecha 02/2020 realizada por la Fundación Nosotros por ti, la entidad tuvo una solicitud previa de AVGM con fecha 09/2017, la cual rechazada. Guanajuato: Previo a la solicitud de declaratoria de AVGM por Violencia Feminicida de fecha 03/2022 realizada por la CNDH, la entidad tuvo dos solicitudes de fechas 06/2009 y 03/2014, las cuales fueron rechazadas. Puebla: Previo a la solicitud de declaratoria de AVGM por Violencia Feminicida de fecha 03/2019 emitida por Comisión Estatal de Derechos Humanos, la entidad tuvo 5 solicitudes de fechas 09/03/2016, 30/03/2016, 20/10/2017, 23/10/2017, 17/11/2017 las cuales fueron acumuladas a la última solicitud de AVGM. Sonora: Tiene dos solicitudes de AVGM, la primera por VF y que fue declarada en 08/2021 y una segunda solicitud de fecha 11/2019 que en principio fue acumulada con la primera solicitud y posteriormente en 12/2020 se des acumuló quedando dos solicitudes de AVGM, una por VF (que ya está declarada) y otra por agravio comparado (que aún se encuentra en etapa de análisis de solicitud). Tlaxcala: Previo a la solicitud de declaratoria de AVGM por Violencia Feminicida de fecha 11/2019 emitida por la Organización de Mujeres de Tercer Milenio, la entidad tuvo una anterior de fecha 08/2016, la cual fue rechazada. | Q107: =[1]Violencia!AE8 -> Datos vigentes
A108: 100 | B108: Violencia | C108: Con declaratoria de Alerta de Violencia de Género contra las Mujeres | D108: Con declaratoria de AVGM por Agravio Comparado | E108: =[1]Violencia!E9 -> Con declaratoria de Alerta de Violencia de Género contra las Mujeres por Agravio Comparado, por entidad federativa. | F108: =[1]Violencia!F9 -> A noviembre 2023 | G108: =[1]Violencia!G9 -> Estatal | H108: =[1]Violencia!H9 -> Situación actual de los procedimientos de Alerta de Violencia de Género contra las Mujeres (AVGM) declaradas a nivel nacional, por tipo de AVGM (Violencia Feminicida, Agravio Comparado y Desaparición), por entidad federativa. | I108: =[1]Violencia!I9 -> Por AVGM declarada y tipo de AVGM. | J108: =[1]Violencia!J9 -> Suma del número total de entidades federativas con AVGM declarada, por tipo de AVGM (Violencia Feminicida, Agravio Comparado y Desaparición), por entidad federativa. | K108: =[1]Violencia!K9 -> Comisión Nacional de los Derechos Humanos (CNDH) con información de la CNDH y de la Comisión Nacional para Prevenir y Erradicar la Violencia contra las Mujeres (Conavim). | L108: =[1]Violencia!L9 -> Fase del procedimiento de Alerta de Violencia de Género. | ... P108: =[1]Violencia!P9 -> 1. Fecha de corte: noviembre 2023. 2. El sitio web de la CONAVIM, sobre Alertas de Violencia de Género contra las Mujeres (AVGM), señala que "*La información que contiene este blog y los links que la acompañan, se actualizan periódicamente.*", pero al no indicar una periodicidad específica, se considera su Periodicidad como No determinada. CDMX: Previo a la solicitud de declaratoria de AVGM por Violencia Feminicida de fecha 02/2020 realizada por la Fundación Nosotros por ti, la entidad tuvo una solicitud previa de AVGM con fecha 09/2017, la cual rechazada. Guanajuato: Previo a la solicitud de declaratoria de AVGM por Violencia Feminicida de fecha 03/2022 realizada por la CNDH, la entidad tuvo dos solicitudes de fechas 06/2009 y 03/2014, las cuales fueron rechazadas. Puebla: Previo a la solicitud de declaratoria de AVGM por Violencia Feminicida de fecha 03/2019 emitida por Comisión Estatal de Derechos Humanos, la entidad tuvo 5 solicitudes de fechas 09/03/2016, 30/03/2016, 20/10/2017, 23/10/2017, 17/11/2017 las cuales fueron acumuladas a la última solicitud de AVGM. Sonora: Tiene dos solicitudes de AVGM, la primera por VF y que fue declarada en 08/2021 y una segunda solicitud de fecha 11/2019 que en principio fue acumulada con la primera solicitud y posteriormente en 12/2020 se des acumuló quedando dos solicitudes de AVGM, una por VF (que ya está declarada) y otra por agravio comparado (que aún se encuentra en etapa de análisis de solicitud). Tlaxcala: Previo a la solicitud de declaratoria de AVGM por Violencia Feminicida de fecha 11/2019 emitida por la Organización de Mujeres de Tercer Milenio, la entidad tuvo una anterior de fecha 08/2016, la cual fue rechazada. | Q108: =[1]Violencia!AE9 -> Datos vigentes
A109: 101 | B109: Violencia | C109: Con declaratoria de Alerta de Violencia de Género contra las Mujeres | D109: Con declaratoria de AVGM por Desaparición | E109: =[1]Violencia!E10 -> Con declaratoria de Alerta de Violencia de Género contra las Mujeres por Desaparición, por entidad federativa. | F109: =[1]Violencia!F10 -> A noviembre 2023 | G109: =[1]Violencia!G10 -> Estatal | H109: =[1]Violencia!H10 -> Situación actual de los procedimientos de Alerta de Violencia de Género contra las Mujeres (AVGM) declaradas a nivel nacional, por tipo de AVGM (Violencia Feminicida, Agravio Comparado y Desaparición), por entidad federativa. | I109: =[1]Violencia!I10 -> Por AVGM declarada y tipo de AVGM. | J109: =[1]Violencia!J10 -> Suma del número total de entidades federativas con AVGM declarada, por tipo de AVGM (Violencia Feminicida, Agravio Comparado y Desaparición), por entidad federativa. | K109: =[1]Violencia!K10 -> Comisión Nacional de los Derechos Humanos (CNDH) con información de la CNDH y de la Comisión Nacional para Prevenir y Erradicar la Violencia contra las Mujeres (Conavim). | L109: =[1]Violencia!L10 -> Fase del procedimiento de Alerta de Violencia de Género. | ... P109: =[1]Violencia!P10 -> 1. Fecha de corte: noviembre 2023. 2. El sitio web de la CONAVIM, sobre Alertas de Violencia de Género contra las Mujeres (AVGM), señala que "*La información que contiene este blog y los links que la acompañan, se actualizan periódicamente.*", pero al no indicar una periodicidad específica, se considera su Periodicidad como No determinada. CDMX: Previo a la solicitud de declaratoria de AVGM por Violencia Feminicida de fecha 02/2020 realizada por la Fundación Nosotros por ti, la entidad tuvo una solicitud previa de AVGM con fecha 09/2017, la cual rechazada. Guanajuato: Previo a la solicitud de declaratoria de AVGM por Violencia Feminicida de fecha 03/2022 realizada por la CNDH, la entidad tuvo dos solicitudes de fechas 06/2009 y 03/2014, las cuales fueron rechazadas. Puebla: Previo a la solicitud de declaratoria de AVGM por Violencia Feminicida de fecha 03/2019 emitida por Comisión Estatal de Derechos Humanos, la entidad tuvo 5 solicitudes de fechas 09/03/2016, 30/03/2016, 20/10/2017, 23/10/2017, 17/11/2017 las cuales fueron acumuladas a la última solicitud de AVGM. Sonora: Tiene dos solicitudes de AVGM, la primera por VF y que fue declarada en 08/2021 y una segunda solicitud de fecha 11/2019 que en principio fue acumulada con la primera solicitud y posteriormente en 12/2020 se des acumuló quedando dos solicitudes de AVGM, una por VF (que ya está declarada) y otra por agravio comparado (que aún se encuentra en etapa de análisis de solicitud). Tlaxcala: Previo a la solicitud de declaratoria de AVGM por Violencia Feminicida de fecha 11/2019 emitida por la Organización de Mujeres de Tercer Milenio, la entidad tuvo una anterior de fecha 08/2016, la cual fue rechazada. | Q109: =[1]Violencia!AE10 -> Datos vigentes
A110: 102 | B110: Violencia | C110: Año de solicitud de Alerta de Violencia de Género contra las Mujeres | D110: Año de solicitud de declaratoria de AVGM por Violencia Feminicida | E110: =[1]Violencia!E11 -> Año de solicitud de declaratoria de Alerta de Violencia de Género contra las Mujeres por Violencia Feminicida, por entidad federativa. | F110: =[1]Violencia!F11 -> A marzo 2022 | G110: =[1]Violencia!G11 -> Estatal | H110: =[1]Violencia!H11 -> Año de solicitud del procedimiento de Alerta de Violencia de Género contra las Mujeres, por tipo de AVGM (Violencia Feminicida, Agravio Comparado y Desaparición), por entidad federativa. | I110: =[1]Violencia!I11 -> Por año de AVGM solicitada | J110: =[1]Violencia!J11 -> Identificación de las entidades federativas que han solicitado AVGM por tipo de AVGM (Violencia Feminicida, Agravio Comparado y Desaparición), por entidad federativa. | K110: =[1]Violencia!K11 -> Comisión Nacional de los Derechos Humanos (CNDH) con información de la CNDH y de la Comisión Nacional para Prevenir y Erradicar la Violencia contra las Mujeres (Conavim). | L110: =[1]Violencia!L11 -> Fase del procedimiento de Alerta de Violencia de Género. | ... P110: =[1]Violencia!P11 -> 1. Fecha de corte: mayo 2022. Posterior a esa fecha, no se ha encontrado actualización en la fuente de información. 2. El sitio web de la CONAVIM, sobre Alertas de Violencia de Género contra las Mujeres (AVGM), señala que "*La información que contiene este blog y los links que la acompañan, se actualizan periódicamente.*", pero al no indicar una periodicidad específica, se considera su Periodicidad como No determinada. CDMX: Previo a la solicitud de declaratoria de AVGM por Violencia Feminicida de fecha 02/2020 realizada por la Fundación Nosotros por ti, la entidad tuvo una solicitud previa de AVGM con fecha 09/2017, la cual rechazada. Guanajuato: Previo a la solicitud de declaratoria de AVGM por Violencia Feminicida de fecha 03/2022 realizada por la CNDH, la entidad tuvo dos solicitudes de fechas 06/2009 y 03/2014, las cuales fueron rechazadas. Puebla: Previo a la solicitud de declaratoria de AVGM por Violencia Feminicida de fecha 03/2019 emitida por Comisión Estatal de Derechos Humanos, la entidad tuvo 5 solicitudes de fechas 09/03/2016, 30/03/2016, 20/10/2017, 23/10/2017, 17/11/2017 las cuales fueron acumuladas a la última solicitud de AVGM. Sonora: Tiene dos solicitudes de AVGM, la primera por VF y que fue declarada en 08/2021 y una segunda solicitud de fecha 11/2019 que en principio fue acumulada con la primera solicitud y posteriormente en 12/2020 se des acumuló quedando dos solicitudes de AVGM, una por VF (que ya está declarada) y otra por agravio comparado (que aún se encuentra en etapa de análisis de solicitud). Tlaxcala: Previo a la solicitud de declaratoria de AVGM por Violencia Feminicida de fecha 11/2019 emitida por la Organización de Mujeres de Tercer Milenio, la entidad tuvo una anterior de fecha 08/2016, la cual fue rechazada. | Q110: =[1]Violencia!AE11 -> Datos vigentes
A111: 103 | B111: Violencia | C111: Año de solicitud de Alerta de Violencia de Género contra las Mujeres | D111: Año de solicitud de declaratoria de AVGM por Agravio Comparado | E111: =[1]Violencia!E12 -> Año de solicitud de declaratoria de Alerta de Violencia de Género contra las Mujeres por Agravio Comparado, por entidad federativa. | F111: =[1]Violencia!F12 -> A marzo 2022 | G111: =[1]Violencia!G12 -> Estatal | H111: =[1]Violencia!H12 -> Año de solicitud del procedimiento de Alerta de Violencia de Género contra las Mujeres, por tipo de AVGM (Violencia Feminicida, Agravio Comparado y Desaparición), por entidad federativa. | I111: =[1]Violencia!I12 -> Por año de AVGM solicitada | J111: =[1]Violencia!J12 -> Identificación de las entidades federativas que han solicitado AVGM por tipo de AVGM (Violencia Feminicida, Agravio Comparado y Desaparición), por entidad federativa. | K111: =[1]Violencia!K12 -> Comisión Nacional de los Derechos Humanos (CNDH) con información de la CNDH y de la Comisión Nacional para Prevenir y Erradicar la Violencia contra las Mujeres (Conavim). | L111: =[1]Violencia!L12 -> Fase del procedimiento de Alerta de Violencia de Género. | ... P111: =[1]Violencia!P12 -> 1. Fecha de corte: mayo 2022. Posterior a esa fecha, no se ha encontrado actualización en la fuente de información. 2. El sitio web de la CONAVIM, sobre Alertas de Violencia de Género contra las Mujeres (AVGM), señala que "*La información que contiene este blog y los links que la acompañan, se actualizan periódicamente.*", pero al no indicar una periodicidad específica, se considera su Periodicidad como No determinada. CDMX: Previo a la solicitud de declaratoria de AVGM por Violencia Feminicida de fecha 02/2020 realizada por la Fundación Nosotros por ti, la entidad tuvo una solicitud previa de AVGM con fecha 09/2017, la cual rechazada. Guanajuato: Previo a la solicitud de declaratoria de AVGM por Violencia Feminicida de fecha 03/2022 realizada por la CNDH, la entidad tuvo dos solicitudes de fechas 06/2009 y 03/2014, las cuales fueron rechazadas. Puebla: Previo a la solicitud de declaratoria de AVGM por Violencia Feminicida de fecha 03/2019 emitida por Comisión Estatal de Derechos Humanos, la entidad tuvo 5 solicitudes de fechas 09/03/2016, 30/03/2016, 20/10/2017, 23/10/2017, 17/11/2017 las cuales fueron acumuladas a la última solicitud de AVGM. Sonora: Tiene dos solicitudes de AVGM, la primera por VF y que fue declarada en 08/2021 y una segunda solicitud de fecha 11/2019 que en principio fue acumulada con la primera solicitud y posteriormente en 12/2020 se des acumuló quedando dos solicitudes de AVGM, una por VF (que ya está declarada) y otra por agravio comparado (que aún se encuentra en etapa de análisis de solicitud). Tlaxcala: Previo a la solicitud de declaratoria de AVGM por Violencia Feminicida de fecha 11/2019 emitida por la Organización de Mujeres de Tercer Milenio, la entidad tuvo una anterior de fecha 08/2016, la cual fue rechazada. | Q111: =[1]Violencia!AE12 -> Datos vigentes
A112: 104 | B112: Violencia | C112: Año de solicitud de Alerta de Violencia de Género contra las Mujeres | D112: Año de solicitud de declaratoria de AVGM por Desaparición | E112: =[1]Violencia!E13 -> Año de solicitud de declaratoria de Alerta de Violencia de Género contra las Mujeres por Desaparición, por entidad federativa. | F112: =[1]Violencia!F13 -> A marzo 2022 | G112: =[1]Violencia!G13 -> Estatal | H112: =[1]Violencia!H13 -> Año de solicitud del procedimiento de Alerta de Violencia de Género contra las Mujeres, por tipo de AVGM (Violencia Feminicida, Agravio Comparado y Desaparición), por entidad federativa. | I112: =[1]Violencia!I13 -> Por año de AVGM solicitada | J112: =[1]Violencia!J13 -> Identificación de las entidades federativas que han solicitado AVGM por tipo de AVGM (Violencia Feminicida, Agravio Comparado y Desaparición), por entidad federativa. | K112: =[1]Violencia!K13 -> Comisión Nacional de los Derechos Humanos (CNDH) con información de la CNDH y de la Comisión Nacional para Prevenir y Erradicar la Violencia contra las Mujeres (Conavim). | L112: =[1]Violencia!L13 -> Fase del procedimiento de Alerta de Violencia de Género. | ... P112: =[1]Violencia!P13 -> 1. Fecha de corte: mayo 2022. Posterior a esa fecha, no se ha encontrado actualización en la fuente de información. 2. El sitio web de la CONAVIM, sobre Alertas de Violencia de Género contra las Mujeres (AVGM), señala que "*La información que contiene este blog y los links que la acompañan, se actualizan periódicamente.*", pero al no indicar una periodicidad específica, se considera su Periodicidad como No determinada. CDMX: Previo a la solicitud de declaratoria de AVGM por Violencia Feminicida de fecha 02/2020 realizada por la Fundación Nosotros por ti, la entidad tuvo una solicitud previa de AVGM con fecha 09/2017, la cual rechazada. Guanajuato: Previo a la solicitud de declaratoria de AVGM por Violencia Feminicida de fecha 03/2022 realizada por la CNDH, la entidad tuvo dos solicitudes de fechas 06/2009 y 03/2014, las cuales fueron rechazadas. Puebla: Previo a la solicitud de declaratoria de AVGM por Violencia Feminicida de fecha 03/2019 emitida por Comisión Estatal de Derechos Humanos, la entidad tuvo 5 solicitudes de fechas 09/03/2016, 30/03/2016, 20/10/2017, 23/10/2017, 17/11/2017 las cuales fueron acumuladas a la última solicitud de AVGM. Sonora: Tiene dos solicitudes de AVGM, la primera por VF y que fue declarada en 08/2021 y una segunda solicitud de fecha 11/2019 que en principio fue acumulada con la primera solicitud y posteriormente en 12/2020 se des acumuló quedando dos solicitudes de AVGM, una por VF (que ya está declarada) y otra por agravio comparado (que aún se encuentra en etapa de análisis de solicitud). Tlaxcala: Previo a la solicitud de declaratoria de AVGM por Violencia Feminicida de fecha 11/2019 emitida por la Organización de Mujeres de Tercer Milenio, la entidad tuvo una anterior de fecha 08/2016, la cual fue rechazada. | Q112: =[1]Violencia!AE13 -> Datos vigentes
A113: 105 | B113: Violencia | C113: Año de declaratoria de Alerta de Violencia de Género contra las Mujeres | D113: Año de declaratoria de AVGM por Violencia Feminicida | E113: =[1]Violencia!E14 -> Año de declaratoria de Alerta de Violencia de Género contra las Mujeres por Violencia Feminicida, por entidad federativa. | F113: =[1]Violencia!F14 -> A noviembre 2023 | G113: =[1]Violencia!G14 -> Estatal | H113: =[1]Violencia!H14 -> Año de declaración del procedimiento de Alerta de Violencia de Género contra las Mujeres, por tipo de AVGM (Violencia Feminicida, Agravio Comparado y Desaparición), por entidad federativa. | I113: =[1]Violencia!I14 -> Por año de AVGM declarada | J113: =[1]Violencia!J14 -> Identificación de las entidades federativas que han declarado AVGM por tipo de AVGM (Violencia Feminicida, Agravio Comparado y Desaparición), por entidad federativa. | K113: =[1]Violencia!K14 -> Comisión Nacional de los Derechos Humanos (CNDH) con información de la CNDH y de la Comisión Nacional para Prevenir y Erradicar la Violencia contra las Mujeres (Conavim). | L113: =[1]Violencia!L14 -> Fase del procedimiento de Alerta de Violencia de Género. | ... P113: =[1]Violencia!P14 -> 1. Fecha de corte: noviembre 2023. 2. El sitio web de la CONAVIM, sobre Alertas de Violencia de Género contra las Mujeres (AVGM), señala que "*La información que contiene este blog y los links que la acompañan, se actualizan periódicamente.*", pero al no indicar una periodicidad específica, se considera su Periodicidad como No determinada. CDMX: Previo a la solicitud de declaratoria de AVGM por Violencia Feminicida de fecha 02/2020 realizada por la Fundación Nosotros por ti, la entidad tuvo una solicitud previa de AVGM con fecha 09/2017, la cual rechazada. Guanajuato: Previo a la solicitud de declaratoria de AVGM por Violencia Feminicida de fecha 03/2022 realizada por la CNDH, la entidad tuvo dos solicitudes de fechas 06/2009 y 03/2014, las cuales fueron rechazadas. Puebla: Previo a la solicitud de declaratoria de AVGM por Violencia Feminicida de fecha 03/2019 emitida por Comisión Estatal de Derechos Humanos, la entidad tuvo 5 solicitudes de fechas 09/03/2016, 30/03/2016, 20/10/2017, 23/10/2017, 17/11/2017 las cuales fueron acumuladas a la última solicitud de AVGM. Sonora: Tiene dos solicitudes de AVGM, la primera por VF y que fue declarada en 08/2021 y una segunda solicitud de fecha 11/2019 que en principio fue acumulada con la primera solicitud y posteriormente en 12/2020 se des acumuló quedando dos solicitudes de AVGM, una por VF (que ya está declarada) y otra por agravio comparado (que aún se encuentra en etapa de análisis de solicitud). Tlaxcala: Previo a la solicitud de declaratoria de AVGM por Violencia Feminicida de fecha 11/2019 emitida por la Organización de Mujeres de Tercer Milenio, la entidad tuvo una anterior de fecha 08/2016, la cual fue rechazada. | Q113: =[1]Violencia!AE14 -> Datos vigentes
A114: 106 | B114: Violencia | C114: Año de declaratoria de Alerta de Violencia de Género contra las Mujeres | D114: Año de declaratoria de AVGM por Agravio Comparado | E114: =[1]Violencia!E15 -> Año de declaratoria de Alerta de Violencia de Género contra las Mujeres por Agravio Comparado, por entidad federativa. | F114: =[1]Violencia!F15 -> A noviembre 2023 | G114: =[1]Violencia!G15 -> Estatal | H114: =[1]Violencia!H15 -> Año de declaración del procedimiento de Alerta de Violencia de Género contra las Mujeres, por tipo de AVGM (Violencia Feminicida, Agravio Comparado y Desaparición), por entidad federativa. | I114: =[1]Violencia!I15 -> Por año de AVGM declarada | J114: =[1]Violencia!J15 -> Identificación de las entidades federativas que han declarado AVGM por tipo de AVGM (Violencia Feminicida, Agravio Comparado y Desaparición), por entidad federativa. | K114: =[1]Violencia!K15 -> Comisión Nacional de los Derechos Humanos (CNDH) con información de la CNDH y de la Comisión Nacional para Prevenir y Erradicar la Violencia contra las Mujeres (Conavim). | L114: =[1]Violencia!L15 -> Fase del procedimiento de Alerta de Violencia de Género. | ... P114: =[1]Violencia!P15 -> 1. Fecha de corte: noviembre 2023. 2. El sitio web de la CONAVIM, sobre Alertas de Violencia de Género contra las Mujeres (AVGM), señala que "*La información que contiene este blog y los links que la acompañan, se actualizan periódicamente.*", pero al no indicar una periodicidad específica, se considera su Periodicidad como No determinada. CDMX: Previo a la solicitud de declaratoria de AVGM por Violencia Feminicida de fecha 02/2020 realizada por la Fundación Nosotros por ti, la entidad tuvo una solicitud previa de AVGM con fecha 09/2017, la cual rechazada. Guanajuato: Previo a la solicitud de declaratoria de AVGM por Violencia Feminicida de fecha 03/2022 realizada por la CNDH, la entidad tuvo dos solicitudes de fechas 06/2009 y 03/2014, las cuales fueron rechazadas. Puebla: Previo a la solicitud de declaratoria de AVGM por Violencia Feminicida de fecha 03/2019 emitida por Comisión Estatal de Derechos Humanos, la entidad tuvo 5 solicitudes de fechas 09/03/2016, 30/03/2016, 20/10/2017, 23/10/2017, 17/11/2017 las cuales fueron acumuladas a la última solicitud de AVGM. Sonora: Tiene dos solicitudes de AVGM, la primera por VF y que fue declarada en 08/2021 y una segunda solicitud de fecha 11/2019 que en principio fue acumulada con la primera solicitud y posteriormente en 12/2020 se des acumuló quedando dos solicitudes de AVGM, una por VF (que ya está declarada) y otra por agravio comparado (que aún se encuentra en etapa de análisis de solicitud). Tlaxcala: Previo a la solicitud de declaratoria de AVGM por Violencia Feminicida de fecha 11/2019 emitida por la Organización de Mujeres de Tercer Milenio, la entidad tuvo una anterior de fecha 08/2016, la cual fue rechazada. | Q114: =[1]Violencia!AE15 -> Datos vigentes
A115: 107 | B115: Violencia | C115: Año de declaratoria de Alerta de Violencia de Género contra las Mujeres | D115: Año de declaratoria de AVGM por Desaparición | E115: =[1]Violencia!E16 -> Año de declaratoria de Alerta de Violencia de Género contra las Mujeres por Desaparición, por entidad federativa. | F115: =[1]Violencia!F16 -> A noviembre 2023 | G115: =[1]Violencia!G16 -> Estatal | H115: =[1]Violencia!H16 -> Año de declaración del procedimiento de Alerta de Violencia de Género contra las Mujeres, por tipo de AVGM (Violencia Feminicida, Agravio Comparado y Desaparición), por entidad federativa. | I115: =[1]Violencia!I16 -> Por año de AVGM declarada | J115: =[1]Violencia!J16 -> Identificación de las entidades federativas que han declarado AVGM por tipo de AVGM (Violencia Feminicida, Agravio Comparado y Desaparición), por entidad federativa. | K115: =[1]Violencia!K16 -> Comisión Nacional de los Derechos Humanos (CNDH) con información de la CNDH y de la Comisión Nacional para Prevenir y Erradicar la Violencia contra las Mujeres (Conavim). | L115: =[1]Violencia!L16 -> Fase del procedimiento de Alerta de Violencia de Género. | ... P115: =[1]Violencia!P16 -> 1. Fecha de corte: noviembre 2023. 2. El sitio web de la CONAVIM, sobre Alertas de Violencia de Género contra las Mujeres (AVGM), señala que "*La información que contiene este blog y los links que la acompañan, se actualizan periódicamente.*", pero al no indicar una periodicidad específica, se considera su Periodicidad como No determinada. CDMX: Previo a la solicitud de declaratoria de AVGM por Violencia Feminicida de fecha 02/2020 realizada por la Fundación Nosotros por ti, la entidad tuvo una solicitud previa de AVGM con fecha 09/2017, la cual rechazada. Guanajuato: Previo a la solicitud de declaratoria de AVGM por Violencia Feminicida de fecha 03/2022 realizada por la CNDH, la entidad tuvo dos solicitudes de fechas 06/2009 y 03/2014, las cuales fueron rechazadas. Puebla: Previo a la solicitud de declaratoria de AVGM por Violencia Feminicida de fecha 03/2019 emitida por Comisión Estatal de Derechos Humanos, la entidad tuvo 5 solicitudes de fechas 09/03/2016, 30/03/2016, 20/10/2017, 23/10/2017, 17/11/2017 las cuales fueron acumuladas a la última solicitud de AVGM. Sonora: Tiene dos solicitudes de AVGM, la primera por VF y que fue declarada en 08/2021 y una segunda solicitud de fecha 11/2019 que en principio fue acumulada con la primera solicitud y posteriormente en 12/2020 se des acumuló quedando dos solicitudes de AVGM, una por VF (que ya está declarada) y otra por agravio comparado (que aún se encuentra en etapa de análisis de solicitud). Tlaxcala: Previo a la solicitud de declaratoria de AVGM por Violencia Feminicida de fecha 11/2019 emitida por la Organización de Mujeres de Tercer Milenio, la entidad tuvo una anterior de fecha 08/2016, la cual fue rechazada. | Q115: =[1]Violencia!AE16 -> Datos vigentes
... A142: 134 | B142: Violencia | C142: Armonización legislativa en materia de no violencia contra las mujeres | D142: Entidades federativas que prohíben el matrimonio antes de los 18 años de edad | E142: =[1]Violencia!E43 -> Número de entidades federativas con Códigos Civiles que prohíben el matrimonio, sin excepciones ni dispensas legales, en menores de edad, por entidad federativa. | F142: =[1]Violencia!F43 -> 2024 | G142: =[1]Violencia!G43 -> Estatal | H142: =[1]Violencia!H43 -> Entidad federativa con Código Civil que prohíbe el matrimonio, sin excepciones ni dispensas legales, en menores de edad, por entidad federativa. En el mapa se visualiza: 1 : lo prohíben. 0 : no lo prohíben. | I142: =[1]Violencia!I43 -> Por Código Civil | J142: =[1]Violencia!J43 -> Número de entidades federativas con Códigos Civiles que prohíben el matrimonio antes de los 18 años y que prohíban la dispensa para el mismo. | K142: =[1]Violencia!K43 -> Cálculos por el Colegio de Geografía (UNAM) y de la CNDH a partir de información de la Cámara de Diputados. | L142: =[1]Violencia!L43 -> Absolutos | ... P142: =[1]Violencia!P43 -> 0 | Q142: =[1]Violencia!AE43 -> Datos vigentes
A143: 135 | B143: Política | C143: Mecanismos para el Adelanto de las Mujeres (MAM) | D143: Instituciones de los Mecanismos para el Adelanto de las Mujeres (MAM) | E143: =[1]Política!D4 -> Instituciones de los Mecanismos para el Adelanto de las Mujeres (MAM), por entidad federativa. | F143: =[1]Política!E4 -> 2024 | G143: =[1]Política!F4 -> Estatal | H143: =[1]Política!G4 -> Los Mecanismos para el Adelanto de la Mujer (MAM) son los mecanismos institucionales (instituciones, secretarías y consejos) para dirigir y coordinar las políticas de igualdad de género en las entidades federativas. Los mecanismos se crearon con diversos grados de institucionalidad y de participación plena: nivel alto, medio y bajo. Nivel alto: instituciones donde la o el titular es parte del Gabinete con participación plena (en México son las "Secretarías"). Medio: instituciones que dependen del gobernador y cuyos titulares no participan en el Gabinete (en México son los "Institutos"). Bajo: instituciones que dependen de una autoridad de menor rango a las anteriores (en México son los "Consejos"). | I143: =[1]Política!H4 -> No aplica. | J143: =[1]Política!I4 -> Los tipos de MAM en México van desde las Secretarías de las Mujeres, Institutos de las Mujeres, hasta los Consejos Estatales de las Mujeres, con sus respectivas variaciones en los nombres. Por Institución de cada Entidad Federativa y son los siguientes: 1= Instituto Aguascalentense de las Mujeres 2= Instituto de la Mujer para el Estado de Baja California 3= Instituto Sudcaliforniano de las Mujeres 4= Instituto de la Mujer del Estado de Campeche 5= Instituto Coahuilense de las Mujeres 6= Instituto Colimense de las Mujeres 7= Secretaría de Igualdad de Género (Chiapas) 8= Instituto Chihuahuense de las Mujeres 9= Secretaría de las Mujeres (Ciudad de México) 10= Instituto Estatal de las Mujeres (Durango) 11= Instituto para las Mujeres Guanajuatenses 12= Secretaría de la Mujer (Guerrero) 13= Instituto Hidalguense de las Mujeres 14= Secretaría de Igualdad Sustantiva entre Mujeres y Hombres (Jalisco) 15= Secretaría de la Mujer (Estado de México) 16= Secretaría de Igualdad Sustantiva y Desarrollo de las Mujeres Michoacanas 17= Instituto de la Mujer para el Estado de Morelos 18= Instituto de la Mujer Nayarita 19= Secretaría de las Mujeres (Nuevo León) 20= Secretaría de las Mujeres (Oaxaca) 21= Secretaría de Igualdad Sustantiva (Puebla) 22= Instituto Queretano de las Mujeres 23= Instituto Quintanorroense de la Mujer 24= Instituto de las Mujeres del Estado de San Luis Potosí 25= Secretaría de las Mujeres (Sinaloa) 26= Instituto Sonorense de las Mujeres 27= Instituto Estatal de las Mujeres (Tabasco) 28= Instituto de las Mujeres en Tamaulipas 29= Instituto Estatal de la Mujer (Tlaxcala) 30= Instituto Veracruzano de las Mujeres 31= Secretaría de las Mujeres (Yucatán) 32= Secretaría de las Mujeres (Zacatecas) | K143: =[1]Política!J4 -> Cálculos por el Colegio de Geografía (UNAM) y de la CNDH a partir de la información del Diario Oficial de la Federación | L143: =[1]Política!K4 -> Por institución | ... P143: =[1]Política!O4 -> 1. Metodología de CEPAL, MAM, abreviada. El responsable del cálculo varía de acuerdo al poder o institución que constituye al organismo, a partir de una Ley el poder legislativo, o si depende de alguna Secretaría, el poder ejecutivo 2.En 2022 la instancia de la Ciudad de México era Instituto de las Mujeres de la Ciudad de México; Nuevo León, Instituto Estatal de las Mujeres; y Sinaloa, Instituto Sinaloense de las Mujeres. | Q143: =[1]Política!AD4 -> Datos vigentes con actualización a 2024.
A144: 136 | B144: Política | C144: Mecanismos para el Adelanto de las Mujeres (MAM) | D144: Nivel jerárquico de los Mecanismos para el Adelanto de las Mujeres (MAM) | E144: =[1]Política!D5 -> Nivel jerárquico de los Mecanismos para el Adelanto de la Mujer (MAM), por entidad federativa. | F144: =[1]Política!E5 -> 2024 | G144: =[1]Política!F5 -> Estatal | H144: =[1]Política!G5 -> Los Mecanismos para el Adelanto de la Mujer (MAM) son los mecanismos institucionales (instituciones, secretarías y consejos) para dirigir y coordinar las políticas de igualdad de género en las entidades federativas. Los mecanismos se crearon con diversos grados de institucionalidad y de participación plena: nivel alto, medio y bajo. Nivel alto: instituciones donde la o el titular es parte del Gabinete con participación plena (en México son las "Secretarías"). Medio: instituciones que dependen del gobernador y cuyos titulares no participan en el Gabinete (en México son los "Institutos"). Bajo: instituciones que dependen de una autoridad de menor rango a las anteriores (en México son los "Consejos"). | I144: =[1]Política!H5 -> No aplica. | J144: =[1]Política!I5 -> Definido por la metodología de la CEPAL, se asignan los valores Alto, Medio y Bajo. Nivel alto, reflejado con un 3: instituciones donde la o el titular es parte del Gabinete con participación plena (en México son las "Secretarías"). Nivel medio, reflejado con un 2: instituciones que dependen del gobernador y cuyos titulares no participan en el Gabinete (en México son los "Institutos"). Nivel bajo, reflejado con un 1: instituciones que dependen de una autoridad de menor rango a las anteriores (en México son los "Consejos"). | K144: =[1]Política!J5 -> Cálculos por el Colegio de Geografía (UNAM) y de la CNDH a partir de la información del Diario Oficial de la Federación | L144: =[1]Política!K5 -> Nivel de jerarquía | ... P144: =[1]Política!O5 -> 1.Metodología de CEPAL, MAM, abreviada. El responsable del cálculo varía de acuerdo al poder o institución que constituye al organismo, a partir de una Ley el poder legislativo, o si depende de alguna Secretaría, el poder ejecutivo. 2.En 2022 la instancia de la Ciudad de México era Instituto de las Mujeres de la Ciudad de México; Nuevo León, Instituto Estatal de las Mujeres; y Sinaloa, Instituto Sinaloense de las Mujeres. | Q144: =[1]Política!AD5 -> Datos vigentes con actualización a 2024.
A145: 137 | B145: Política | C145: Titularidad del poder ejecutivo según sexo y según periodo electoral | D145: Porcentaje estatal de mujeres gobernadoras desde la publicación de la LGIMH y según periodo electoral | E145: =[1]Política!D6 -> Porcentaje de mujeres gobernadoras a cargo desde la publicación de la LGIMH y según periodo electoral, por entidad federativa. | F145: =[1]Política!E6 -> 2006-2012; 2012-2018;2018-2024 | G145: =[1]Política!F6 -> Estatal | H145: =[1]Política!G6 -> Distribución porcentual de las mujeres responsables del poder ejecutivo en la dirección de las entidades federativas desde la publicación de la Ley General de Igualdad entre Mujeres y Hombres (LGIMH) y por periodo electoral, por entidad federativa. | I145: =[1]Política!H6 -> Por sexo y periodo electoral | J145: =[1]Política!I6 -> Suma del número de titulares del poder ejecutivo según sexo (mujeres/hombres) de un periodo electoral, entre el total de titulares del poder ejecutivo a nivel estatal del mismo perioro electoral, multiplicado por 100, desde la publicación de la Ley General de Igualdad entre Mujeres y Hombres (LGIMH) | K145: =[1]Política!J6 -> Cálculos por el Colegio de Geografía (UNAM) y de la CNDH a partir a partir de los datos obtenidos del Instituto Nacional Electoral (INE). | L145: =[1]Política!K6 -> Participación en puestos | ... P145: =[1]Política!O6 -> 1. La participación se presenta concentrada en los períodos de agosto de 2006 a julio de 2012, agosto de 2012 a julio de 2018 y de agosto de 2018 a julio de 2024 en el indicador debido a que los años en que inicia el período de gobierno varían, por lo anterior se reporta la información de tres períodos. 2. Para los periodos electorales se tomaron en cuenta únicamente a gubernaturas ganadas en procesos electorales, es decir, titulares y no interinos. | Q145: =[1]Política!AD6 -> Datos vigentes con actualización a 2024.
A146: 138 | B146: Política | C146: Titularidad del poder ejecutivo según sexo y según periodo electoral | D146: Porcentaje estatal de hombres gobernadores desde la publicación de la LGIMH y según periodo electoral | E146: =[1]Política!D7 -> Porcentaje de hombres gobernadores a cargo desde la publicación de la LGIMH y según periodo electoral, por entidad federativa. | F146: =[1]Política!E7 -> 2006-2012; 2012-2018;2018-2024 | G146: =[1]Política!F7 -> Estatal | H146: =[1]Política!G7 -> Distribución porcentual de las mujeres responsables del poder ejecutivo en la dirección de las entidades federativas desde la publicación de la Ley General de Igualdad entre Mujeres y Hombres (LGIMH) y por periodo electoral, por entidad federativa. | I146: =[1]Política!H7 -> Por sexo y periodo electoral | J146: =[1]Política!I7 -> Suma del número de titulares del poder ejecutivo según sexo (mujeres/hombres) de un periodo electoral, entre el total de titulares del poder ejecutivo a nivel estatal del mismo perioro electoral, multiplicado por 100, desde la publicación de la Ley General de Igualdad entre Mujeres y Hombres (LGIMH) | K146: =[1]Política!J7 -> Cálculos por el Colegio de Geografía (UNAM) y de la CNDH a partir a partir de los datos obtenidos del Instituto Nacional Electoral (INE). | L146: =[1]Política!K7 -> Participación en puestos | ... P146: =[1]Política!O7 -> 1. La participación se presenta concentrada en los períodos de agosto de 2006 a julio de 2012, agosto de 2012 a julio de 2018 y de agosto de 2018 a a julio de 202 en el indicador debido a que los años en que inicia el período de gobierno varían, por lo anterior se reporta la información de tres períodos. 2. Para los periodos electorales se tomaron en cuenta únicamente a gubernaturas ganadas en procesos electorales, es decir, titulares y no interinos. | Q146: =[1]Política!AD7 -> Datos vigentes con actualización a 2024.
A147: 139 | B147: Política | C147: Titularidad del poder ejecutivo según sexo y según periodo electoral | D147: Número de periodos electorales desde la publicación de la LGIMH | E147: =[1]Política!D8 -> Número de periodos electorales desde la publicación de la LGIMH, por entidad federativa. | F147: =[1]Política!E8 -> 2006-2012; 2012-2018;2018-2024 | G147: =[1]Política!F8 -> Estatal | H147: =[1]Política!G8 -> Distribución de los números de periodos electorales desde la publicación de la Ley General de Igualdad entre Mujeres y Hombres (LGIMH) | I147: =[1]Política!H8 -> No aplica. | J147: =[1]Política!I8 -> Conteo de periodos electorales según el número de titulares desde la publicación de la Ley General de Igualdad entre Mujeres y Hombres (LGIMH). | K147: =[1]Política!J8 -> Cálculos por el Colegio de Geografía (UNAM) y de la CNDH a partir a partir de los datos obtenidos del Instituto Nacional Electoral (INE). | L147: =[1]Política!K8 -> No aplica | ... P147: =[1]Política!O8 -> 1. La participación se presenta concentrada en los períodos de agosto de 2006 a julio de 2012, agosto de 2012 a julio de 2018 y de agosto de 2018 a julio de 2024 en el indicador debido a que los años en que inicia el período de gobierno varían, por lo anterior se reporta la información de tres períodos. 2. Para los periodos electorales se tomaron en cuenta únicamente a gubernaturas ganadas en procesos electorales, es decir, titulares y no interinos. | Q147: =[1]Política!AD8 -> Datos vigentes con actualización a 2024.
A148: 140 | B148: Política | C148: Índice de avance en la armonización legislativa en materia de igualdad, no discriminación, no violencia contra las mujeres y trata de personas | D148: NA | E148: =[1]Política!D9 -> Índice de avance en la armonización legislativa en materia de igualdad, no discriminación, no violencia contra las mujeres y trata de personas | F148: =[1]Política!E9 -> 2024 | G148: =[1]Política!F9 -> Estatal | H148: =[1]Política!G9 -> Referencia a la inclusión en el orden jurídico en las entidades federativas de las leyes en materia de igualdad, violencia contra las mujeres, discriminación y trata de personas, así como sus reglamentos. | I148: =[1]Política!H9 -> No aplica. | J148: =[1]Política!I9 -> Suma de leyes y/o reglamentos señalados (en caso de existir se asigna el valor 1 de no ser así se asigna 0), multiplicados por el valor de ponderación de 12.5. | K148: =[1]Política!J9 -> Cálculos por el Colegio de Geografía (UNAM) y de la CNDH a partir de la metodología del indicador del Instituto Nacional de las Mujeres (INMUJERES). | L148: =[1]Política!K9 -> Índice | ... P148: =[1]Política!O9 -> 0 | Q148: =[1]Política!AD9 -> Datos vigentes con actualización a 2024.
A149: 141 | B149: Política | C149: Organizaciones certificadas en el Modelo de Equidad de Género según su tipo de administración | D149: Organizaciones públicas certificadas en el Modelo de Equidad de Género (2003-2015) | E149: =[1]Política!D10 -> Instituciones públicas capacitadas y certificadas en el modelo de equidad de género (MEG), por entidad federativa. | F149: =[1]Política!E10 -> 2005, 2010 y 2013. | G149: =[1]Política!F10 -> Estatal | H149: =[1]Política!G10 -> Organizaciones certificadas en el Modelo de Equidad de Género a partir de la Norma Mexicana de Igualdad NMX-R-025-SCFI-2012 (2003-2015) | I149: =[1]Política!H10 -> Públicas y privadas. | J149: =[1]Política!I10 -> Conteo por año y entidad federativa de las organizaciones públicas y privadas a partir de su año inicial de certificación en el modelo de igualdad laboral entre mujeres y hombres que tuvieron una vigencia al 31 de diciembre del 2015. | K149: =[1]Política!J10 -> Cálculos por el Colegio de Geografía (UNAM) a partir de la metodología del indicador del Instituto Nacional de las Mujeres (INMUJERES). | L149: =[1]Política!K10 -> Organismos con la Certificación NMX-R-025-SCFI-2012 | ... P149: =[1]Política!O10 -> 1.Los datos disponibles corresponden a los años 2005, 2010 y 2013 considerando el año de certificación inicial con vigencia al 2015. 2.Con corte al segundo trimestre de 2024, la fuente oficial de información no cuenta con actualización de datos posterior al 2015. | Q149: =[1]Política!AD10 -> La fuente oficial de información no cuenta con actualización de datos.
A150: 142 | B150: Política | C150: Organizaciones certificadas en el Modelo de Equidad de Género según su tipo de administración | D150: Organizaciones privadas certificadas en el Modelo de Equidad de Género (2003-2015) | E150: =[1]Política!D11 -> Instituciones privadas capacitadas y certificadas en el modelo de equidad de género (MEG), por entidad federativa. | F150: =[1]Política!E11 -> 2005, 2010 y 2013. | G150: =[1]Política!F11 -> Estatal | H150: =[1]Política!G11 -> Organizaciones certificadas en el Modelo de Equidad de Género a partir de la Norma Mexicana de Igualdad NMX-R-025-SCFI-2012 (2003-2015) | I150: =[1]Política!H11 -> Públicas y privadas. | J150: =[1]Política!I11 -> Conteo por año y entidad federativa de las organizaciones públicas y privadas a partir de su año inicial de certificación en el modelo de igualdad laboral entre mujeres y hombres que tuvieron una vigencia al 31 de diciembre del 2015. | K150: =[1]Política!J11 -> Cálculos por el Colegio de Geografía (UNAM) a partir de la metodología del indicador del Instituto Nacional de las Mujeres (INMUJERES). | L150: =[1]Política!K11 -> Organismos con la Certificación NMX-R-025-SCFI-2012 | ... P150: =[1]Política!O11 -> 1. Los datos disponibles corresponden a los años 2005, 2010 y 2013 considerando el año de certificación inicial con vigencia al 2015. 2.Con corte al segundo trimestre de 2024, la fuente oficial de información no cuenta con actualización de datos posterior al 2015. | Q150: =[1]Política!AD11 -> La fuente oficial de información no cuenta con actualización de datos.
A151: 143 | B151: Política | C151: Armonización de las leyes y reglamentos estatales por año de publicación | D151: Año de publicación de las leyes análogas a la Ley para la Igualdad entre mujeres y hombres (el valor indica el año) | E151: =[1]Política!D12 -> Año de publicación de las leyes análogas a la Ley para la Igualdad entre mujeres y hombres, por entidad federativa | F151: =[1]Política!E12 -> 2005-2024 | G151: =[1]Política!F12 -> Estatal | H151: =[1]Política!G12 -> Entidades federativas que han armonizado sus leyes con la Ley General para la Igualdad entre Mujeres y Hombres. | I151: =[1]Política!H12 -> Por publicación de ley o reglamento. | J151: =[1]Política!I12 -> Identificación de las entidades federativas que han publicado sus leyes o reglamentos análogos a las existentes con respecto a la Ley o Reglamento General o Federal correspondiente. | K151: =[1]Política!J12 -> Cálculos por el Colegio de Geografía (UNAM) y de la CNDH a partir de información de la Cámara de Diputados. | L151: =[1]Política!K12 -> Años | ... P151: =[1]Política!O12 -> El valor indica el año. Fecha de corte: agosto 2024. | Q151: =[1]Política!AD12 -> Datos vigentes con actualización a 2024.
A152: 144 | B152: Política | C152: Armonización de las leyes y reglamentos estatales por año de publicación | D152: Año de publicación de los reglamentos análogos al Reglamento de Ley para la Igualdad entre mujeres y hombres (el valor indica el año) | E152: =[1]Política!D13 -> Año de publicación de los reglamentos análogos al Reglamento de Ley para la Igualdad entre mujeres y hombres, por entidad federativa | F152: =[1]Política!E13 -> 2010-2024 | G152: =[1]Política!F13 -> Estatal | H152: =[1]Política!G13 -> Entidades federativas que han armonizado sus reglamentos con el Reglamento de Ley para la Igualdad entre mujeres y hombres. | I152: =[1]Política!H13 -> Por publicación de ley o reglamento. | J152: =[1]Política!I13 -> Identificación de las entidades federativas que han publicado sus leyes o reglamentos análogos a las existentes con respecto a la Ley o Reglamento General o Federal correspondiente. | K152: =[1]Política!J13 -> Cálculos por el Colegio de Geografía (UNAM) y de la CNDH a partir de información de la Cámara de Diputados. | L152: =[1]Política!K13 -> Años | ... P152: =[1]Política!O13 -> El valor indica el año. Fecha de corte: agosto 2024. | Q152: =[1]Política!AD13 -> Datos vigentes con actualización a 2024.
A153: 145 | B153: Política | C153: Armonización de las leyes y reglamentos estatales por año de publicación | D153: Año de publicación de las leyes análogas a la Ley de Acceso de las Mujeres a una Vida Libre de Violencia (el valor indica el año) | E153: =[1]Política!D14 -> Año de publicación de las leyes análogas a la Ley de Acceso de las Mujeres a una Vida Libre de Violencia, por entidad federativa. | F153: =[1]Política!E14 -> 2007-2024 | G153: =[1]Política!F14 -> Estatal | H153: =[1]Política!G14 -> Entidades federativas que han armonizado sus leyes con la Ley de Acceso de las Mujeres a una Vida Libre de Violencia. | I153: =[1]Política!H14 -> Por publicación de ley o reglamento. | J153: =[1]Política!I14 -> Identificación de las entidades federativas que han publicado sus leyes o reglamentos análogos a las existentes con respecto a la Ley o Reglamento General o Federal correspondiente. | K153: =[1]Política!J14 -> Cálculos por el Colegio de Geografía (UNAM) y de la CNDH a partir de información de la Cámara de Diputados. | L153: =[1]Política!K14 -> Años | ... P153: =[1]Política!O14 -> El valor indica el año. Fecha de corte: agosto 2024. | Q153: =[1]Política!AD14 -> Datos vigentes con actualización a 2024.
A154: 146 | B154: Política | C154: Armonización de las leyes y reglamentos estatales por año de publicación | D154: Año de publicación de los reglamentos análogos al Reglamento de Ley de Acceso de las Mujeres a una Vida Libre de Violencia (el valor indica el año) | E154: =[1]Política!D15 -> Año de publicación de los reglamentos análogos al Reglamento de Ley de Acceso de las Mujeres a una Vida Libre de Violencia, por entidad federativa. | F154: =[1]Política!E15 -> 2008-2024 | G154: =[1]Política!F15 -> Estatal | H154: =[1]Política!G15 -> Entidades federativas que han armonizado sus reglamentos con el Reglamento de Ley de Acceso de las Mujeres a una Vida Libre de Violencia. | I154: =[1]Política!H15 -> Por publicación de ley o reglamento. | J154: =[1]Política!I15 -> Identificación de las entidades federativas que han publicado sus leyes o reglamentos análogos a las existentes con respecto a la Ley o Reglamento General o Federal correspondiente. | K154: =[1]Política!J15 -> Cálculos por el Colegio de Geografía (UNAM) y de la CNDH a partir de información de la Cámara de Diputados. | L154: =[1]Política!K15 -> Años | ... P154: =[1]Política!O15 -> El valor indica el año. Fecha de corte: agosto 2024. | Q154: =[1]Política!AD15 -> Datos vigentes con actualización a 2024.
... A159: 151 | B159: Política | C159: Monitoreo de legalización del aborto | D159: NA | E159: =[1]Política!D20 -> Número de códigos penales que han despenalizado el aborto hasta la doceava semana de gestación, según entidad federativa | F159: =[1]Política!E20 -> 2024 | G159: =[1]Política!F20 -> Estatal | H159: =[1]Política!G20 -> Situación de la regulación de los Códigos Penales, con relación a la despenalización del aborto hasta la doceava semana de gestación, por entidad federativa. | I159: =[1]Política!H20 -> Por situación de despenalización. | J159: =[1]Política!I20 -> Identificación de las entidades federativas que han publicado en sus códigos penales la despenalización del aborto hasta la doceava semana de gestación. | K159: =[1]Política!J20 -> CNDH, a través del Programa de Asuntos de la Mujer y de Igualdad entre Mujeres y Hombres (PAMIMH), a partir de información de los decretos de los Congresos de las entidades federativas. | L159: =[1]Política!K20 -> Código penal de entidad federativa. | ... P159: =[1]Política!O20 -> 1. De las entidades señaladas, sólo Sinaloa no hace referencia al término aborto, sino interrupción del embarazo y se considera delito después de la décima tercer semana de gestación. 2. El valor de 1 en el mapa indica que se tiene la despenalización del aborto en el código penal, en caso contrario se indica con 0. 3. En agosto de 2024, Aguascalientes redujo a 6 semanas el plazo para poder acceder al aborto sin penalización. | Q159: =[1]Política!AD20 -> Datos vigentes con actualización a 2024.
A160: 152 | B160: Espacio | C160: Índice de Desarrollo Humano (IDH) | D160: Índice de Desarrollo Humano estatal | E160: =[1]Espacio!D4 -> Índice de Desarrollo Humano (IDH), por entidad federativa. | F160: =[1]Espacio!E4 -> 2008, 2010, 2012 y 2015. | G160: =[1]Espacio!F4 -> Estatal | H160: =[1]Espacio!G4 -> No aplica. | I160: =[1]Espacio!H4 -> El Índice de Desarrollo Humano (IDH) se creó para hacer hincapié en que la ampliación de las oportunidades de las personas debería ser el criterio más importante para evaluar los resultados en materia de desarrollo. El IDH mide el progreso conseguido por un país en tres dimensiones básicas del desarrollo humano: disfrutar de una vida larga y saludable, acceso a educación y nivel de vida digno (ONU). | J160: =[1]Espacio!I4 -> El IDH es una medida sinóptica para medir el Desarrollo Humano y las variables utilizadas según dimensión son las siguientes: 1. Salud: se utilizó un índice compuesto que refleja condiciones de salud en los hogares: protección de salud, a través del IGSS o de un seguro, número de personas por dormitorio, tipo de acceso a agua y saneamiento y tipo de piso en la vivienda. 2. Educación: indicador compuesto que incluye la esperanza educativa en niños y la escolaridad alcanzada por adultos mayores de 25 años. 3. Nivel de vida: Se incluyó un agregado del ingreso laboral y no laboral familiar, ajustado a precios internacionales (en dólares PPA per cápita). Ingresos laborales y no laborales per cápita. Siendo 0 indicador de completa igualdad y 1 indicador de completa desigualdad. | K160: =[1]Espacio!J4 -> Cálculos por el Colegio de Geografía (UNAM) y de la CNDH a partir de la información del Programa de las Naciones Unidas para el Desarrollo (PNUD) en México. | L160: =[1]Espacio!K4 -> Relativos | ... P160: =[1]Espacio!O4 -> Con corte al segundo trimestre de 2024, la fuente oficial de información no cuenta con actualización de datos a nivel estatal posterior al 2015. | Q160: =[1]Espacio!AD4 -> Datos vigentes al no haber actualización por parte de la fuente de información.
A161: 153 | B161: Espacio | C161: Índice de Desarrollo Humano (IDH) | D161: Índice de Desarrollo Humano estatal de mujeres | E161: =[1]Espacio!D5 -> Índice de Desarrollo Humano (IDH) de mujeres, por entidad federativa. | F161: =[1]Espacio!E5 -> 2008, 2010 y 2012. | G161: =[1]Espacio!F5 -> Estatal | H161: =[1]Espacio!G5 -> Por sexo. | I161: =[1]Espacio!H5 -> El Índice de Desarrollo Humano (IDH) se creó para hacer hincapié en que la ampliación de las oportunidades de las personas debería ser el criterio más importante para evaluar los resultados en materia de desarrollo. El IDH mide el progreso conseguido por un país en tres dimensiones básicas del desarrollo humano: disfrutar de una vida larga y saludable, acceso a educación y nivel de vida digno (ONU). | J161: =[1]Espacio!I5 -> El IDH es una medida sinóptica para medir el Desarrollo Humano y las variables utilizadas según dimensión son las siguientes: 1. Salud: se utilizó un índice compuesto que refleja condiciones de salud en los hogares: protección de salud, a través del IGSS o de un seguro, número de personas por dormitorio, tipo de acceso a agua y saneamiento y tipo de piso en la vivienda. 2. Educación: indicador compuesto que incluye la esperanza educativa en niños y la escolaridad alcanzada por adultos mayores de 25 años. 3. Nivel de vida: Se incluyó un agregado del ingreso laboral y no laboral familiar, ajustado a precios internacionales (en dólares PPA per cápita). Ingresos laborales y no laborales per cápita. Siendo 0 indicador de completa igualdad y 1 indicador de completa desigualdad. | K161: =[1]Espacio!J5 -> Cálculos por el Colegio de Geografía (UNAM) y de la CNDH a partir de la información del Programa de las Naciones Unidas para el Desarrollo (PNUD) en México. | L161: =[1]Espacio!K5 -> Relativos | ... P161: =[1]Espacio!O5 -> Con corte al segundo trimestre de 2024, la fuente oficial de información no cuenta con actualización de datos a nivel estatal posterior al 2012. | Q161: =[1]Espacio!AD5 -> Datos vigentes al no haber actualización por parte de la fuente de información.
A162: 154 | B162: Espacio | C162: Índice de Desarrollo Humano (IDH) | D162: Índice de Desarrollo Humano estatal de hombres | E162: =[1]Espacio!D6 -> Índice de Desarrollo Humano (IDH) de hombres, por entidad federativa. | F162: =[1]Espacio!E6 -> 2008, 2010 y 2012. | G162: =[1]Espacio!F6 -> Estatal | H162: =[1]Espacio!G6 -> Por sexo. | I162: =[1]Espacio!H6 -> El Índice de Desarrollo Humano (IDH) se creó para hacer hincapié en que la ampliación de las oportunidades de las personas debería ser el criterio más importante para evaluar los resultados en materia de desarrollo. El IDH mide el progreso conseguido por un país en tres dimensiones básicas del desarrollo humano: disfrutar de una vida larga y saludable, acceso a educación y nivel de vida digno (ONU). | J162: =[1]Espacio!I6 -> El IDH es una medida sinóptica para medir el Desarrollo Humano y las variables utilizadas según dimensión son las siguientes: 1. Salud: se utilizó un índice compuesto que refleja condiciones de salud en los hogares: protección de salud, a través del IGSS o de un seguro, número de personas por dormitorio, tipo de acceso a agua y saneamiento y tipo de piso en la vivienda. 2. Educación: indicador compuesto que incluye la esperanza educativa en niños y la escolaridad alcanzada por adultos mayores de 25 años. 3. Nivel de vida: Se incluyó un agregado del ingreso laboral y no laboral familiar, ajustado a precios internacionales (en dólares PPA per cápita). Ingresos laborales y no laborales per cápita. Siendo 0 indicador de completa igualdad y 1 indicador de completa desigualdad. | K162: =[1]Espacio!J6 -> Cálculos por el Colegio de Geografía (UNAM) y de la CNDH a partir de la información del Programa de las Naciones Unidas para el Desarrollo (PNUD) en México. | L162: =[1]Espacio!K6 -> Relativos | ... P162: =[1]Espacio!O6 -> Con corte al segundo trimestre de 2024, la fuente oficial de información no cuenta con actualización de datos a nivel estatal posterior al 2012. | Q162: =[1]Espacio!AD6 -> Datos vigentes al no haber actualización por parte de la fuente de información.
A163: 155 | B163: Espacio | C163: Índice de Desarrollo Humano relativo al Género (IDG) | D163: NA | E163: =[1]Espacio!D7 -> Índice de Desarrollo Relativo al Género (IDG), por entidad federativa. | F163: =[1]Espacio!E7 -> 2006, 2007, 2008, 2009 y 2010. | G163: =[1]Espacio!F7 -> Estatal | H163: =[1]Espacio!G7 -> No aplica. | I163: =[1]Espacio!H7 -> Mientras el IDH mide el progreso medio en desarrollo humano para todas las personas, el IDG ajusta su cálculo para reflejar las desigualdades sociales y económicas entre hombres y mujeres. | J163: =[1]Espacio!I7 -> El IDG es una medida sinóptica para medir la desigualdad de género en tres aspectos importantes del Desarrollo Humano: Vida larga y saludable (medido por la esperanza de vida al nacer de cada sexo) Educación (medida por la tasa de alfabetización de adultos y tasa bruta combinada de matriculación en educación primaria, secundaria y terciaria por sexo) Nivel de vida digno (medido por la estimación de ingresos percibidos por sexo). Siendo 0 indicador de completa igualdad y 1 indicador de completa desigualdad. | K163: =[1]Espacio!J7 -> Cálculos de la CNDH a partir de la información del Programa de las Naciones Unidas para el Desarrollo (PNUD) en México. | L163: =[1]Espacio!K7 -> Relativos | ... P163: =[1]Espacio!O7 -> Con corte al segundo trimestre de 2024, la fuente oficial de información no cuenta con actualización de datos a nivel estatal posterior al 2012. | Q163: =[1]Espacio!AD7
A164: 156 | B164: Espacio | C164: Índice de Desigualdad de Género (IDG) | D164: NA | E164: =[1]Espacio!D8 -> Índice de Desigualdad de Género (IDG), por entidad federativa. | F164: =[1]Espacio!E8 -> 2008, 2010 y 2012. | G164: =[1]Espacio!F8 -> Estatal | H164: =[1]Espacio!G8 -> No aplica. | I164: =[1]Espacio!H8 -> El IDG permite conocer la pérdida en desarrollo humano debida a la desigualdad entre mujeres y hombres al medir la diferencia en el logro entre ambos sexos en tres dimensiones: salud reproductiva, empoderamiento y mercado laboral. Cuando el IDG tiene un valor cercano a cero, el panorama de desarrollo es igualitario; cuando se aproxima a uno, las desventajas de las mujeres frente a los hombres son amplias. | J164: =[1]Espacio!I8 -> El IDG (nueva metodología) es una medida sinóptica para medir la desigualdad de género en tres aspectos importantes del Desarrollo Humano: 1. Empoderamiento. El componente de empoderamiento del IDG refleja el acceso a escaños en el Congreso y a niveles secundarios y terciarios de educación. 2. Salud Reproductiva. La dimensión de salud reproductiva incluye la tasa de mortalidad materna y la tasa de fecundidad adolescente. 3. Mercado Laboral. La participación de la mujer en la fuerza de trabajo es otra dimensión del IDG. | K164: =[1]Espacio!J8 -> Cálculos de la CNDH a partir de la información del Programa de las Naciones Unidas para el Desarrollo (PNUD) en México. | L164: =[1]Espacio!K8 -> Relativos | ... P164: =[1]Espacio!O8 -> Con corte al segundo trimestre de 2024, la fuente oficial de información no cuenta con actualización de datos a nivel estatal posterior al 2012. | Q164: =[1]Espacio!AD8 -> Datos vigentes al no haber actualización por parte de la fuente de información.
A165: 157 | B165: Espacio | C165: Población propietaria de vivienda particular habitada según sexo. | D165: Porcentaje estatal de mujeres propietarias de viviendas particulares habitadas | E165: =[1]Espacio!D9 -> Porcentaje de mujeres propietarias de viviendas particulares habitadas, por entidad federativa. | F165: =[1]Espacio!E9 -> 2015 y 2020 | G165: =[1]Espacio!F9 -> Estatal | H165: =[1]Espacio!G9 -> Por sexo. | I165: =[1]Espacio!H9 -> Distribución porcentual de mujeres que son jurídica y físicamente dueñas de una vivienda particular, es decir, una edificación de construcción fija que fue diseñada, construida o adaptada para la habitación de un hogar o familia, que tiene entrada independiente desde la calle, campo o un espacio común (al momento del levantamiento está en condiciones de habitarse y no se usa exclusivamente para realizar alguna actividad económica), en la fecha de referencia al levantamiento por entidad federativa. | J165: =[1]Espacio!I9 -> Suma de la población propietaria de viviendas particulares, es decir, una edificación de construcción fija que fue diseñada, construida o adaptada para la habitación de un hogar o familia, que tiene entrada independiente desde la calle, campo o un espacio común (al momento del levantamiento está en condiciones de habitarse y no se usa exclusivamente para realizar alguna actividad económica), según sexo (mujeres/hombres), entre la población total de personas propietarias de viviendas particulares, multiplicado por 100. | K165: =[1]Espacio!J9 -> Cálculos por el Colegio de Geografía (UNAM) y de la CNDH a partir de la información del Instituto Nacional de Estadística y Geografía (INEGI) | L165: =[1]Espacio!K9 -> Relativos | ... P165: =[1]Espacio!O9 -> Con corte al segundo trimestre de 2024, la fuente oficial de información no cuenta con actualización de datos a nivel estatal posterior al 2020. | Q165: =[1]Espacio!AD9 -> Datos vigentes por periodicidad quinquenal.
A166: 158 | B166: Espacio | C166: Población propietaria de vivienda particular habitada según sexo. | D166: Porcentaje estatal de hombres propietarios de viviendas particulares habitadas | E166: =[1]Espacio!D10 -> Porcentaje de hombres propietarios de viviendas particulares habitadas, por entidad federativa. | F166: =[1]Espacio!E10 -> 2015 y 2020 | G166: =[1]Espacio!F10 -> Estatal | H166: =[1]Espacio!G10 -> Por sexo. | I166: =[1]Espacio!H10 -> Distribución porcentual de hombres que son jurídica y físicamente dueños de una vivienda particular, es decir, una edificación de construcción fija que fue diseñada, construida o adaptada para la habitación de un hogar o familia, que tiene entrada independiente desde la calle, campo o un espacio común (al momento del levantamiento está en condiciones de habitarse y no se usa exclusivamente para realizar alguna actividad económica), en la fecha de referencia al levantamiento por entidad federativa. | J166: =[1]Espacio!I10 -> Suma de la población propietaria de viviendas particulares, es decir, una edificación de construcción fija que fue diseñada, construida o adaptada para la habitación de un hogar o familia, que tiene entrada independiente desde la calle, campo o un espacio común (al momento del levantamiento está en condiciones de habitarse y no se usa exclusivamente para realizar alguna actividad económica), según sexo (mujeres/hombres), entre la población total de personas propietarias de viviendas particulares, multiplicado por 100. | K166: =[1]Espacio!J10 -> Cálculos por el Colegio de Geografía (UNAM) y de la CNDH a partir de la información del Instituto Nacional de Estadística y Geografía (INEGI) | L166: =[1]Espacio!K10 -> Relativos | ... P166: =[1]Espacio!O10 -> Con corte al segundo trimestre de 2024, la fuente oficial de información no cuenta con actualización de datos a nivel estatal posterior al 2020. | Q166: =[1]Espacio!AD10 -> Datos vigentes por periodicidad quinquenal.
A167: 159 | B167: Educativa | C167: Porcentaje estatal de la población alfabeta de 15 y más años | D167: NA | E167: =[1]Educativa!D4 -> Porcentaje de la población alfabeta de 15 años y más, por entidad federativa. | F167: =[1]Educativa!E4 -> 2010, 2015 y 2020. | G167: =[1]Educativa!F4 -> Estatal | H167: =[1]Educativa!G4 -> Distribución porcentual de las personas de 15 y más años de edad que saben leer y escribir un recado, en la fecha de referencia al levantamiento, por entidad federativa. | I167: =[1]Educativa!H4 -> No aplica. | J167: =[1]Educativa!I4 -> Suma de la población alfabeta de 15 años y más, entre el total de la población total de 15 años y más, multiplicado por 100. | K167: =[1]Educativa!J4 -> Cálculos por el Colegio de Geografía (UNAM) y de la CNDH a partir de la información del Instituto Nacional de Estadística y Geografía (INEGI) | L167: =[1]Educativa!K4 -> Porcentaje | ... P167: =[1]Educativa!O4 | Q167: =[1]Educativa!AD4 -> Datos vigentes por periodicidad quinquenal.
A168: 160 | B168: Educativa | C168: Población de alumnado que asiste a la escuela según sexo y nivel educativo | D168: Porcentaje estatal de alumnas mujeres que asisten a la educación básica | E168: =[1]Educativa!D5 -> Porcentaje de alumnas mujeres que asiste a la educación básica, por entidad federativa. | F168: =[1]Educativa!E5 -> Periodos 2008-2009, 2009-2010, 2010-2011, 2011-2012, 2012-2013, 2013-2014, 2014-2015, 2015-2016, 2016-2017, 2017-2018, 2018-2019, 2019-2020, 2020-2021, 2021-2022 y 2022-2023. | G168: =[1]Educativa!F5 -> Estatal | H168: =[1]Educativa!G5 -> Distribución porcentual de mujeres en el sistema educativo nacional de acuerdo al nivel de educación que cursan, en la fecha de referencia al levantamiento, por entidad federativa. | I168: =[1]Educativa!H5 -> Por sexo, ciclo escolar y nivel educativo. | J168: =[1]Educativa!I5 -> Suma de la población según sexo (mujeres/hombres) que asiste al sistema educativo nacional de acuerdo al nivel de educación que cursan, entre la matrícula total del sistema educativo (de ese nivel y periodo), multiplicado por 100. | K168: =[1]Educativa!J5 -> Cálculos por el Colegio de Geografía (UNAM) y de la CNDH a partir de la información de la Secretaría de Educación Pública (SEP). | L168: =[1]Educativa!K5 -> Porcentaje | ... P168: =[1]Educativa!O5 -> La fuente de información indica que los datos para el ciclo 2023-2024 son aún cifras preliminares, por lo cual aún no se ha trabajado con esta información. | Q168: =[1]Educativa!AD5 -> Datos vigentes, ya que la fuente de información indica que los datos del ciclo 2023-2024 son aún cifras preliminares, por lo que no se trabajará con estos datos en tanto no se publiquen los datos definitivos.
A169: 161 | B169: Educativa | C169: Población de alumnado que asiste a la escuela según sexo y nivel educativo | D169: Porcentaje estatal de alumnos hombres que asiste a la educación básica | E169: =[1]Educativa!D6 -> Porcentaje de alumnos hombres que asiste a la educación básica, por entidad federativa. | F169: =[1]Educativa!E6 -> Periodos 2008-2009, 2009-2010, 2010-2011, 2011-2012, 2012-2013, 2013-2014, 2014-2015, 2015-2016, 2016-2017, 2017-2018, 2018-2019, 2019-2020, 2020-2021, 2021-2022 y 2022-2023. | G169: =[1]Educativa!F6 -> Estatal | H169: =[1]Educativa!G6 -> Distribución porcentual de hombres en el sistema educativo nacional de acuerdo al nivel de educación que cursan, en la fecha de referencia al levantamiento, por entidad federativa. | I169: =[1]Educativa!H6 -> Por sexo, ciclo escolar y nivel educativo. | J169: =[1]Educativa!I6 -> Suma de la población según sexo (mujeres/hombres) que asiste al sistema educativo nacional de acuerdo al nivel de educación que cursan, entre la matrícula total del sistema educativo (de ese nivel y periodo), multiplicado por 100. | K169: =[1]Educativa!J6 -> Cálculos por el Colegio de Geografía (UNAM) y de la CNDH a partir de la información de la Secretaría de Educación Pública (SEP). | L169: =[1]Educativa!K6 -> Porcentaje | ... P169: =[1]Educativa!O6 -> La fuente de información indica que los datos para el ciclo 2023-2024 son aún cifras preliminares, por lo cual aún no se ha trabajado con esta información. | Q169: =[1]Educativa!AD6 -> Datos vigentes, ya que la fuente de información indica que los datos del ciclo 2023-2024 son aún cifras preliminares, por lo que no se trabajará con estos datos en tanto no se publiquen los datos definitivos.
A170: 162 | B170: Educativa | C170: Población de alumnado que asiste a la escuela según sexo y nivel educativo | D170: Porcentaje estatal de alumnas mujeres que asisten a la educación media superior | E170: =[1]Educativa!D7 -> Porcentaje de alumnas mujeres que asiste a la educación media superior, por entidad federativa. | F170: =[1]Educativa!E7 -> Periodos 2008-2009, 2009-2010, 2010-2011, 2012-2013, 2013-2014, 2014-2015, 2015-2016, 2017-2018, 2018-2019, 2019-2020, 2020-2021, 2021-2022 y 2022-2023. | G170: =[1]Educativa!F7 -> Estatal | H170: =[1]Educativa!G7 -> Distribución porcentual de mujeres en el sistema educativo nacional de acuerdo al nivel de educación que cursan, en la fecha de referencia al levantamiento, por entidad federativa. | I170: =[1]Educativa!H7 -> Por sexo, ciclo escolar y nivel educativo. | J170: =[1]Educativa!I7 -> Suma de la población según sexo (mujeres/hombres) que asiste al sistema educativo nacional de acuerdo al nivel de educación que cursan, entre la matrícula total del sistema educativo (de ese nivel y periodo), multiplicado por 100. | K170: =[1]Educativa!J7 -> Cálculos por el Colegio de Geografía (UNAM) y de la CNDH a partir de la información de la Secretaría de Educación Pública (SEP). | L170: =[1]Educativa!K7 -> Porcentaje | ... P170: =[1]Educativa!O7 -> La fuente de información indica que los datos para el ciclo 2023-2024 son aún cifras preliminares, por lo cual aún no se ha trabajado con esta información. | Q170: =[1]Educativa!AD7 -> Datos vigentes, ya que la fuente de información indica que los datos del ciclo 2023-2024 son aún cifras preliminares, por lo que no se trabajará con estos datos en tanto no se publiquen los datos definitivos.
A171: 163 | B171: Educativa | C171: Población de alumnado que asiste a la escuela según sexo y nivel educativo | D171: Porcentaje estatal de alumnos hombres que asiste a la educación media superior | E171: =[1]Educativa!D8 -> Porcentaje de alumnos hombres que asiste a la educación media superior, por entidad federativa. | F171: =[1]Educativa!E8 -> Periodos 2008-2009, 2009-2010, 2010-2011, 2012-2013, 2013-2014, 2014-2015, 2015-2016, 2017-2018, 2018-2019, 2019-2020, 2020-2021, 2021-2022 y 2022-2023. | G171: =[1]Educativa!F8 -> Estatal | H171: =[1]Educativa!G8 -> Distribución porcentual de hombres en el sistema educativo nacional de acuerdo al nivel de educación que cursan, en la fecha de referencia al levantamiento, por entidad federativa. | I171: =[1]Educativa!H8 -> Por sexo, ciclo escolar y nivel educativo. | J171: =[1]Educativa!I8 -> Suma de la población según sexo (mujeres/hombres) que asiste al sistema educativo nacional de acuerdo al nivel de educación que cursan, entre la matrícula total del sistema educativo (de ese nivel y periodo), multiplicado por 100. | K171: =[1]Educativa!J8 -> Cálculos por el Colegio de Geografía (UNAM) y de la CNDH a partir de la información de la Secretaría de Educación Pública (SEP). | L171: =[1]Educativa!K8 -> Porcentaje | ... P171: =[1]Educativa!O8 -> La fuente de información indica que los datos para el ciclo 2023-2024 son aún cifras preliminares, por lo cual aún no se ha trabajado con esta información. | Q171: =[1]Educativa!AD8 -> Datos vigentes, ya que la fuente de información indica que los datos del ciclo 2023-2024 son aún cifras preliminares, por lo que no se trabajará con estos datos en tanto no se publiquen los datos definitivos.
A172: 164 | B172: Educativa | C172: Población de alumnado que asiste a la escuela según sexo y nivel educativo | D172: Porcentaje estatal de alumnas mujeres que asisten a la educación superior | E172: =[1]Educativa!D9 -> Porcentaje de alumnas mujeres que asiste a la educación superior, por entidad federativa. | F172: =[1]Educativa!E9 -> Periodos 2008-2009, 2009-2010, 2010-2011, 2012-2013, 2013-2014, 2014-2015, 2015-2016, 2017-2018, 2018-2019, 2019-2020, 2020-2021, 2021-2022 y 2022-2023. | G172: =[1]Educativa!F9 -> Estatal | H172: =[1]Educativa!G9 -> Distribución porcentual de mujeres en el sistema educativo nacional de acuerdo al nivel de educación que cursan, en la fecha de referencia al levantamiento, por entidad federativa. | I172: =[1]Educativa!H9 -> Por sexo, ciclo escolar y nivel educativo. | J172: =[1]Educativa!I9 -> Suma de la población según sexo (mujeres/hombres) que asiste al sistema educativo nacional de acuerdo al nivel de educación que cursan, entre la matrícula total del sistema educativo (de ese nivel y periodo), multiplicado por 100. | K172: =[1]Educativa!J9 -> Cálculos por el Colegio de Geografía (UNAM) y de la CNDH a partir de la información de la Secretaría de Educación Pública (SEP). | L172: =[1]Educativa!K9 -> Porcentaje | ... P172: =[1]Educativa!O9 -> La fuente de información indica que los datos para el ciclo 2023-2024 son aún cifras preliminares, por lo cual aún no se ha trabajado con esta información. | Q172: =[1]Educativa!AD9 -> Datos vigentes, ya que la fuente de información indica que los datos del ciclo 2023-2024 son aún cifras preliminares, por lo que no se trabajará con estos datos en tanto no se publiquen los datos definitivos.
A173: 165 | B173: Educativa | C173: Población de alumnado que asiste a la escuela según sexo y nivel educativo | D173: Porcentaje estatal de alumnos hombres que asiste a la educación superior | E173: =[1]Educativa!D10 -> Porcentaje de alumnos hombres que asiste a la educación superior, por entidad federativa. | F173: =[1]Educativa!E10 -> Periodos 2008-2009, 2009-2010, 2010-2011, 2012-2013, 2013-2014, 2014-2015, 2015-2016, 2017-2018, 2018-2019, 2019-2020, 2020-2021, 2021-2022 y 2022-2023. | G173: =[1]Educativa!F10 -> Estatal | H173: =[1]Educativa!G10 -> Distribución porcentual de hombres en el sistema educativo nacional de acuerdo al nivel de educación que cursan, en la fecha de referencia al levantamiento, por entidad federativa. | I173: =[1]Educativa!H10 -> Por sexo, ciclo escolar y nivel educativo. | J173: =[1]Educativa!I10 -> Suma de la población según sexo (mujeres/hombres) que asiste al sistema educativo nacional de acuerdo al nivel de educación que cursan, entre la matrícula total del sistema educativo (de ese nivel y periodo), multiplicado por 100. | K173: =[1]Educativa!J10 -> Cálculos por el Colegio de Geografía (UNAM) y de la CNDH a partir de la información de la Secretaría de Educación Pública (SEP). | L173: =[1]Educativa!K10 -> Porcentaje | ... P173: =[1]Educativa!O10 -> La fuente de información indica que los datos para el ciclo 2023-2024 son aún cifras preliminares, por lo cual aún no se ha trabajado con esta información. | Q173: =[1]Educativa!AD10 -> Datos vigentes, ya que la fuente de información indica que los datos del ciclo 2023-2024 son aún cifras preliminares, por lo que no se trabajará con estos datos en tanto no se publiquen los datos definitivos.
A174: 166 | B174: Educativa | C174: Grado promedio de escolaridad | D174: Grado promedio estatal de escolaridad | E174: =[1]Educativa!D11 -> Grado promedio de escolaridad, por entidad federativa. | F174: =[1]Educativa!E11 -> 2010, 2015 y 2020. | G174: =[1]Educativa!F11 -> Estatal | H174: =[1]Educativa!G11 -> Número de años de educación formal que, en promedio, han aprobado las personas de 15 años y más de edad, en el Sistema Educativo Nacional, en la fecha de referencia al levantamiento, por entidad federativa. Permite conocer el nivel de educación de una población determinada. | I174: =[1]Educativa!H11 -> No aplica. | J174: =[1]Educativa!I11 -> Promedio de años de escolaridad formal: suma del total de los años aprobados por cada persona, desde el primer año de primaria hasta el último año del grado alcanzado, de las personas de 15 años y más de edad, entre el total de la población de 15 años y más de edad. | K174: =[1]Educativa!J11 -> Cálculos por el Colegio de Geografía (UNAM) y de la CNDH a partir de la información del Instituto Nacional de Estadística y Geografía (INEGI) | L174: =[1]Educativa!K11 -> Promedio de años | ... P174: =[1]Educativa!O11 -> Los grados promedios presentan 1 decimal por origen de la información. | Q174: =[1]Educativa!AD11 -> Datos vigentes por periodicidad quinquenal.
A175: 167 | B175: Educativa | C175: Grado promedio de escolaridad | D175: Grado promedio estatal de escolaridad de mujeres | E175: =[1]Educativa!D12 -> Grado promedio de escolaridad de mujeres, por entidad federativa. | F175: =[1]Educativa!E12 -> 2010, 2015 y 2020. | G175: =[1]Educativa!F12 -> Estatal | H175: =[1]Educativa!G12 -> Número de años de educación formal que, en promedio, han aprobado las mujeres de 15 años y más de edad, en el Sistema Educativo Nacional, en la fecha de referencia al levantamiento, por entidad federativa. Permite conocer el nivel de educación de una población determinada. | I175: =[1]Educativa!H12 -> Por sexo. | J175: =[1]Educativa!I12 -> Promedio de años de escolaridad formal: suma del total de los años aprobados por cada mujer, desde el primer año de primaria hasta el último año del grado alcanzado, de las mujeres de 15 años y más de edad, entre el total de la población de 15 años y más de edad. | K175: =[1]Educativa!J12 -> Cálculos por el Colegio de Geografía (UNAM) y de la CNDH a partir de la información del Instituto Nacional de Estadística y Geografía (INEGI) | L175: =[1]Educativa!K12 -> Promedio de años | ... P175: =[1]Educativa!O12 -> Los grados promedios presentan 1 decimal por origen de la información. | Q175: =[1]Educativa!AD12 -> Datos vigentes por periodicidad quinquenal.
A176: 168 | B176: Educativa | C176: Grado promedio de escolaridad | D176: Grado promedio estatal de escolariad de hombres | E176: =[1]Educativa!D13 -> Grado promedio de escolariad de hombres, por entidad federativa. | F176: =[1]Educativa!E13 -> 2010, 2015 y 2020. | G176: =[1]Educativa!F13 -> Estatal | H176: =[1]Educativa!G13 -> Número de años de educación formal que, en promedio, han aprobado los hombres de 15 años y más de edad, en el Sistema Educativo Nacional, en la fecha de referencia al levantamiento, por entidad federativa. Permite conocer el nivel de educación de una población determinada. | I176: =[1]Educativa!H13 -> Por sexo. | J176: =[1]Educativa!I13 -> Promedio de años de escolaridad formal: suma del total de los años aprobados por cada hombre, desde el primer año de primaria hasta el último año del grado alcanzado, de los hombres de 15 años y más de edad, entre el total de la población de 15 años y más de edad. | K176: =[1]Educativa!J13 -> Cálculos por el Colegio de Geografía (UNAM) y de la CNDH a partir de la información del Instituto Nacional de Estadística y Geografía (INEGI) | L176: =[1]Educativa!K13 -> Promedio de años | ... P176: =[1]Educativa!O13 -> Los grados promedios presentan 1 decimal por origen de la información. | Q176: =[1]Educativa!AD13 -> Datos vigentes por periodicidad quinquenal.
A177: 169 | B177: Educativa | C177: Tasa de absorción según sexo y nivel educativo | D177: Tasa de absorción estatal de mujeres en educación básica | E177: =[1]Educativa!D14 -> Tasa de absorción de mujeres en educación básica, por entidad federativa. | F177: =[1]Educativa!E14 -> Periodos 2009-2010, 2010-2011, 2014-2015, 2015-2016, 2021-2022 y 2022-2023 | G177: =[1]Educativa!F14 -> Estatal | H177: =[1]Educativa!G14 -> Número de alumnos y alumnas en total de nuevo ingreso a 1° de secundaria o media superior en un determinado ciclo escolar, por cada cien egresados del nivel educativo precedente en el ciclo escolar previo, en la fecha de referencia al levantamiento, por entidad federativa. | I177: =[1]Educativa!H14 -> Por sexo y nivel educativo. | J177: =[1]Educativa!I14 -> Número de alumnos y alumnas en total de nuevo ingreso a 1° de grado educativo N en un determinado ciclo escolar, por cada cien egresados del nivel educativo N precedente en el ciclo escolar previo. | K177: =[1]Educativa!J14 -> Cálculos por el Colegio de Geografía (UNAM) y de la CNDH a partir de la información del Sistema de Información y Gestión Educativa (SIGED) | L177: =[1]Educativa!K14 -> Porcentaje | ... P177: =[1]Educativa!O14 -> 1. Solo se considera secundaria como referente del nivel de educación básico. 2. La tasa de absorción provee una estimación del tránsito educativo entre niveles. El indicador pone de manifiesto la capacidad del sistema para atender a la población que ha finalizado el nivel educativo precedente y que se incorpora a secundaria o a media superior. 3. Con corte al segundo trimestre de 2024, la fuente de información indica que los datos para el ciclo 2023-2024 son aún cifras preliminares, por lo cual aún no se ha trabajado con esta información. | Q177: =[1]Educativa!AD14 -> Datos vigentes, ya que la fuente de información indica que los datos del ciclo 2023-2024 son aún cifras preliminares, por lo que no se trabajará con estos datos en tanto no se publiquen los datos definitivos.
A178: 170 | B178: Educativa | C178: Tasa de absorción según sexo y nivel educativo | D178: Tasa de absorción estatal de hombres en educación básica | E178: =[1]Educativa!D15 -> Tasa de absorción de hombres en educación básica, por entidad federativa. | F178: =[1]Educativa!E15 -> Periodos 2009-2010, 2010-2011, 2014-2015, 2015-2016, 2021-2022 y 2022-2023 | G178: =[1]Educativa!F15 -> Estatal | H178: =[1]Educativa!G15 -> Número de alumnos y alumnas en total de nuevo ingreso a 1° de secundaria o media superior en un determinado ciclo escolar, por cada cien egresados del nivel educativo precedente en el ciclo escolar previo, en la fecha de referencia al levantamiento, por entidad federativa. | I178: =[1]Educativa!H15 -> Por sexo y nivel educativo. | J178: =[1]Educativa!I15 -> Número de alumnos y alumnas en total de nuevo ingreso a 1° de grado educativo N en un determinado ciclo escolar, por cada cien egresados del nivel educativo N precedente en el ciclo escolar previo. | K178: =[1]Educativa!J15 -> Cálculos por el Colegio de Geografía (UNAM) y de la CNDH a partir de la información del Sistema de Información y Gestión Educativa (SIGED) | L178: =[1]Educativa!K15 -> Porcentaje | ... P178: =[1]Educativa!O15 -> 1. Solo se considera secundaria como referente del nivel de educación básico. 2. La tasa de absorción provee una estimación del tránsito educativo entre niveles. El indicador pone de manifiesto la capacidad del sistema para atender a la población que ha finalizado el nivel educativo precedente y que se incorpora a secundaria o a media superior. 3. Con corte al segundo trimestre de 2024, la fuente de información indica que los datos para el ciclo 2023-2024 son aún cifras preliminares, por lo cual aún no se ha trabajado con esta información. | Q178: =[1]Educativa!AD15 -> Datos vigentes, ya que la fuente de información indica que los datos del ciclo 2023-2024 son aún cifras preliminares, por lo que no se trabajará con estos datos en tanto no se publiquen los datos definitivos.
... A188: 180 | B188: Educativa | C188: Población de alumnado que asiste a la escuela según sexo | D188: Porcentaje estatal de alumnos hombres que asisten a la escuela (Educación Básica a Superior) | E188: =[1]Educativa!D25 -> Porcentaje de alumnos hombres que asiste a la escuela (Educación Básica a Superior), por entidad federativa. | F188: =[1]Educativa!E25 -> Periodos 2008-2009, 2009-2010, 2010-2011, 2012-2013, 2013-2014, 2014-2015, 2015-2016, 2017-2018, 2018-2019, 2019-2020, 2020-2021, 2021-2022 y 2022-2023. | G188: =[1]Educativa!F25 -> Estatal | H188: =[1]Educativa!G25 -> Distribución porcentual de alumnado en el sistema educativo nacional según sexo (mujeres y hombres), por ciclo escolar, en la fecha de referencia al levantamiento, por entidad federativa. | I188: =[1]Educativa!H25 -> Por sexo y ciclo escolar. | J188: =[1]Educativa!I25 -> Suma de la población estudiantil matriculada, es decir, inscrito (de primer ingreso y de reingreso), en educación básica, media superior y superior según sexo, por entidad federativa, entre el total de población estudiantil matriculada en educación básica, media superior y superior total, multiplicado por 100. | K188: =[1]Educativa!J25 -> Cálculos por el Colegio de Geografía (UNAM) y de la CNDH a partir de la información de la Secretaría de Educación Pública (SEP). | L188: =[1]Educativa!K25 -> Porcentaje | ... P188: =[1]Educativa!O25 -> 1. Con corte al segundo trimestre de 2024, la fuente de información indica que los datos para el ciclo 2023-2024 son aún cifras preliminares, por lo cual aún no se ha trabajado con esta información. | Q188: =[1]Educativa!AD25 -> Datos vigentes, ya que la fuente de información indica que los datos del ciclo 2023-2024 son aún cifras preliminares, por lo que no se trabajará con estos datos en tanto no se publiquen los datos definitivos.
A189: 181 | B189: Sanitaria | C189: Población con afiliación a servicios de salud | D189: Porcentaje estatal de la población con afiliación a servicios de salud | E189: =[1]Sanitaria!D4 -> Porcentaje de la población con afiliación a servicios de salud, por entidad federativa. | F189: =[1]Sanitaria!E4 -> 2005, 2010, 2015 y 2020. | G189: =[1]Sanitaria!F4 -> Estatal | H189: =[1]Sanitaria!G4 -> Distribución porcentual de población total con afiliación a servicios de salud, en la fecha de referencia al levantamiento, por entidad federativa. | I189: =[1]Sanitaria!H4 -> No aplica. | J189: =[1]Sanitaria!I4 -> Suma de la población con afiliación a servicios de salud según sexo (mujeres/hombres) según entidad federativa, entre el total de la población, multiplicado por 100. | K189: =[1]Sanitaria!J4 -> Cálculos por el Colegio de Geografía (UNAM) y de la CNDH a partir de la información del Instituto Nacional de Estadística y Geografía (INEGI) | L189: =[1]Sanitaria!K4 -> Porcentaje | ... P189: =[1]Sanitaria!O4 -> Para el Censo 2010 se nombra a la variable como Población total con derechohabiencia y número, se consideró “Con derechohabiencia” por mujeres y hombres. Para el 2015 en la Encuesta Intercensal la variable fue “Condición de Afiliación a servicios de salud” por Total y Sexo y finalmente para el censo 2020, la variable es: Población Total “Con Afiliación a los servicios de salud”. | Q189: =[1]Sanitaria!AD4 -> Datos vigentes por periodicidad quinquenal.
A190: 182 | B190: Sanitaria | C190: Población con afiliación a servicios de salud | D190: Porcentaje estatal de mujeres con afiliación a servicios de salud | E190: =[1]Sanitaria!D5 -> Porcentaje de mujeres con afiliación a servicios de salud, por entidad federativa. | F190: =[1]Sanitaria!E5 -> 2005, 2010, 2015 y 2020. | G190: =[1]Sanitaria!F5 -> Estatal | H190: =[1]Sanitaria!G5 -> Distribución porcentual de mujeres con afiliación a servicios de salud, en la fecha de referencia al levantamiento, por entidad federativa. | I190: =[1]Sanitaria!H5 -> Por sexo. | J190: =[1]Sanitaria!I5 -> Suma de la población con afiliación a servicios de salud según sexo (mujeres/hombres) según entidad federativa, entre el total de la población, multiplicado por 100. | K190: =[1]Sanitaria!J5 -> Cálculos por el Colegio de Geografía (UNAM) y de la CNDH a partir de la información del Instituto Nacional de Estadística y Geografía (INEGI) | L190: =[1]Sanitaria!K5 -> Porcentaje | ... P190: =[1]Sanitaria!O5 -> Para el Censo 2010 se nombra a la variable como Población total con derechohabiencia y número, se consideró “Con derechohabiencia” por mujeres y hombres. Para el 2015 en la Encuesta Intercensal la variable fue “Condición de Afiliación a servicios de salud” por Total y Sexo y finalmente para el censo 2020, la variable es: Población Total “Con Afiliación a los servicios de salud”. | Q190: =[1]Sanitaria!AD5 -> Datos vigentes por periodicidad quinquenal.
A191: 183 | B191: Sanitaria | C191: Población con afiliación a servicios de salud | D191: Porcentaje estatal de hombres con afiliación a servicios de salud | E191: =[1]Sanitaria!D6 -> Porcentaje de hombres con afiliación a servicios de salud, por entidad federativa. | F191: =[1]Sanitaria!E6 -> 2005, 2010, 2015 y 2020. | G191: =[1]Sanitaria!F6 -> Estatal | H191: =[1]Sanitaria!G6 -> Distribución porcentual de hombres con afiliación a servicios de salud, en la fecha de referencia al levantamiento, por entidad federativa. | I191: =[1]Sanitaria!H6 -> Por sexo. | J191: =[1]Sanitaria!I6 -> Suma de la población con afiliación a servicios de salud según sexo (mujeres/hombres) según entidad federativa, entre el total de la población, multiplicado por 100. | K191: =[1]Sanitaria!J6 -> Cálculos por el Colegio de Geografía (UNAM) y de la CNDH a partir de la información del Instituto Nacional de Estadística y Geografía (INEGI) | L191: =[1]Sanitaria!K6 -> Porcentaje | ... P191: =[1]Sanitaria!O6 -> Para el Censo 2010 se nombra a la variable como Población total con derechohabiencia y número, se consideró “Con derechohabiencia” por mujeres y hombres. Para el 2015 en la Encuesta Intercensal la variable fue “Condición de Afiliación a servicios de salud” por Total y Sexo y finalmente para el censo 2020, la variable es: Población Total “Con Afiliación a los servicios de salud”. | Q191: =[1]Sanitaria!AD6 -> Datos vigentes por periodicidad quinquenal.
A192: 184 | B192: Sanitaria | C192: Demanda insatisfecha de planificación familiar | D192: NA | E192: =[1]Sanitaria!D7 -> Demanda insatisfecha de planificación familiar, por entidad federativa. | F192: =[1]Sanitaria!E7 -> 2006, 2009, 2014 y 2018. | G192: =[1]Sanitaria!F7 -> Estatal | H192: =[1]Sanitaria!G7 -> Distribución porcentual de mujeres definidas como fértiles y sexualmente activas, entre 15-49 años de edad, independiente de su estado civil, y que reportan que no desean tener más hijos (límite: número de hijos) o que desean retrasar el nacimiento de su próximo hijo por al menos dos años o no están decididas sobre el momento de su próximo nacimiento (espacio: tiempo) y que no usan ningún método anticonceptivo (CEPAL), en la fecha de referencia al levantamiento, por entidad federativa. El concepto de demanda insatisfecha de planificación familiar alude a la brecha entre las intenciones reproductivas de la mujer y su comportamiento anticonceptivo. | I192: =[1]Sanitaria!H7 -> No aplica. | J192: =[1]Sanitaria!I7 -> De acuerdo a CEPAL, en el numerador, todas las mujeres definidas como fértiles de 15-49 años que tienen una necesidad insatisfecha de planificación familiar y el denominador el número total de mujeres definidas como fértiles de 15-49 años de edad. El resultado se multiplica por 100. Las mujeres con una necesidad insatisfecha incluye: todas las mujeres embarazadas (casadas o en unión consensual) cuyos embarazos fueron no deseados o inoportunos en el momento de la concepción; todas las mujeres con amenorrea postparto (casadas o en unión consensual) que no utilizan la planificación familiar y cuyo último nacimiento fue no deseado o inoportuno; y todas las mujeres fértiles (casadas o en unión consensual) que no están embarazadas ni amenorreicas después del parto, y que, o no quieren tener más hijos (límite), o que desean posponer el nacimiento de un hijo por lo menos durante dos años o no saben cuándo o si se quieren tener otro hijo (espacio), y no usan ningún método anticonceptivo. En el numerador se excluye las mujeres embarazadas y con amenorrea que se quedaron embarazadas involuntariamente debido a la falla del método anticonceptivo (se supone que estas mujeres están en la necesidad de un mejor método anticonceptivo). Las mujeres infértiles también se excluyen de la definición. | K192: =[1]Sanitaria!J7 -> Cálculos por el Colegio de Geografía (UNAM) y de la CNDH, a partir de información del Consejo Nacional de Población (CONAPO). | L192: =[1]Sanitaria!K7 -> Porcentaje | ... P192: =[1]Sanitaria!O7 -> 1. Con corte al segundo trimestre de 2024, el INEGI ha publicado ya la ENADID 2023, pero el CONAPO no ha publicado actualización de los datos de salud reproductiva, para obtener la información. 2. El INEGI señaló en mayo de 2024 que, a partir de la determinación de la ENADID como Información de Interés Nacional, la periodicidad de la ENADID se volverá quinquenal. | Q192: =[1]Sanitaria!AD7 -> Datos vigentes por periodicidad quinquenal, sin embargo, la fuente oficial de información no cuenta con actualización de datos.
A193: 185 | B193: Sanitaria | C193: Muerte materna | D193: Tasa de mortalidad materna estatal | E193: =[1]Sanitaria!D8 -> Tasa de mortalidad materna, por entidad federativa. | F193: =[1]Sanitaria!E8 -> 2006, 2012, 2017, 2018, 2019, 2020, 2021 y 2022. | G193: =[1]Sanitaria!F8 -> Estatal | H193: =[1]Sanitaria!G8 -> Número de muertes de mujeres debido a complicaciones del embarazo o parto, durante el embarazo o dentro de los 42 días posteriores al término de éste, de acuerdo con las mujeres en edad reproductiva, por entidad federativa (algunas definiciones especifican que la mujer debe haber estado embarazada dentro de las 3 a 12 semanas anteriores a la muerte). | I193: =[1]Sanitaria!H8 -> No aplica. | J193: =[1]Sanitaria!I8 -> Número de muertes maternas por cada 100.000 mujeres en edad reproductiva (15 a 49). | K193: =[1]Sanitaria!J8 -> Cálculos por el Colegio de Geografía (UNAM) y de la CNDH a partir de la información del Instituto Nacional de Estadística y Geografía (INEGI) y Secretaría de Salud (SSA). | L193: =[1]Sanitaria!K8 -> Tasa | ... P193: =[1]Sanitaria!O8 -> Con corte al segundo trimestre de 2024, la fuente de información no arroja datos en la consulta posteriores al año 2022. | Q193: =[1]Sanitaria!AD8 -> Datos vigentes debido a que la fuente oficial de información no cuenta con actualización de datos.
A194: 186 | B194: Sanitaria | C194: Muerte materna | D194: Razón de mortalidad materna estatal | E194: =[1]Sanitaria!D9 -> Razón de mortalidad materna, por entidad federativa. | F194: =[1]Sanitaria!E9 -> 2005, 2006, 2007, 2008, 2009, 2010, 2011, 2012, 2013, 2014, 2015, 2016, 2017, 2018, 2019, 2020, 2021 y 2022. | G194: =[1]Sanitaria!F9 -> Estatal | H194: =[1]Sanitaria!G9 -> Número de muertes de mujeres debido a complicaciones del embarazo o parto, durante el embarazo o dentro de los 42 días posteriores al término de éste, de acuerdo con los nacimientos vivos durante el mismo periodo de tiempo, por entidad federativa (algunas definiciones especifican que la mujer debe haber estado embarazada dentro de las 3 a 12 semanas anteriores a la muerte). | I194: =[1]Sanitaria!H9 -> No aplica. | J194: =[1]Sanitaria!I9 -> Número de muertes maternas por cada 100.000 nacimientos vivos durante el mismo periodo de tiempo. | K194: =[1]Sanitaria!J9 -> Cálculos por el Colegio de Geografía (UNAM) y de la CNDH, a partir de información del Consejo Nacional de Población (CONAPO). | L194: =[1]Sanitaria!K9 -> Razón | ... P194: =[1]Sanitaria!O9 -> 1. Con corte al segundo trimestre de 2024, la fuente de información no ha publicado actualización de los datos posteriores a 2022. 2. La fuente de información original (Protocolo de San Salvador) dejó de publicar la información hasta 2018. La Secretaría de Salud retomó este indicador. | Q194: =[1]Sanitaria!AD9 -> Datos vigentes debido a que la fuente oficial de información no cuenta con actualización de datos.
A195: 187 | B195: Sanitaria | C195: Mujeres con pareja y usuarias de métodos anticonceptivos | D195: Porcentaje estatal de mujeres con pareja y usuarias de métodos anticonceptivos modernos | E195: =[1]Sanitaria!D10 -> Porcentaje de mujeres en edad fértil con pareja usuarias de métodos anticonceptivos modernos, por entidad federativa. | F195: =[1]Sanitaria!E10 -> 2009 y 2014. | G195: =[1]Sanitaria!F10 -> Estatal | H195: =[1]Sanitaria!G10 -> Distribución porcentual de mujeres en edad fértil y sexualmente activas con pareja y usuarias de métodos anticonceptivos modernos, en la fecha de referencia al levantamiento, por entidad federativa. | I195: =[1]Sanitaria!H10 -> No aplica. | J195: =[1]Sanitaria!I10 -> Suma de la población total de mujeres en edad fértil y sexualmente activas con pareja y usuarias de métodos anticonceptivos modernos, entre el total de las y los encuestados, multiplicado por 100. | K195: =[1]Sanitaria!J10 -> Cálculos por el Colegio de Geografía (UNAM) a partir de la información del Consejo Nacional de Población (CONAPO) | L195: =[1]Sanitaria!K10 -> Porcentaje | ... P195: =[1]Sanitaria!O10 -> Con corte al segundo trimestre de 2024, la fuente de información no ha publicado actualización de los datos posteriores a 2014. | Q195: =[1]Sanitaria!AD10 -> Datos vigentes debido a que la fuente oficial de información no cuenta con actualización de datos.
A196: 188 | B196: Sanitaria | C196: Mujeres con pareja y usuarias de métodos anticonceptivos | D196: Porcentaje estatal de mujeres con pareja y usuarias de métodos anticonceptivos moderno con participación masculina en la prevalencia de éstos | E196: =[1]Sanitaria!D11 -> Porcentaje de mujeres en edad fértil con pareja usuarias de métodos anticonceptivos moderno con participación masculina en la prevalencia anticonceptiva, por entidad federativa. | F196: =[1]Sanitaria!E11 -> 2009 y 2014. | G196: =[1]Sanitaria!F11 -> Estatal | H196: =[1]Sanitaria!G11 -> Distribución porcentual de mujeres en edad fértil y sexualmente activas con pareja y usuarias de métodos anticonceptivos modernos con participación masculina (de la pareja) en la prevalencia anticonceptiva, en la fecha de referencia al levantamiento, por entidad federativa. | I196: =[1]Sanitaria!H11 -> No aplica. | J196: =[1]Sanitaria!I11 -> Suma de la población total de mujeres en edad fértil y sexualmente activas con pareja y usuarias de métodos anticonceptivos modernos con participación masculina (de la pareja) en la prevalencia anticonceptiva, entre el total de las y los encuestados, multiplicado por 100. | K196: =[1]Sanitaria!J11 -> Cálculos por el Colegio de Geografía (UNAM) a partir de la información del Consejo Nacional de Población (CONAPO) | L196: =[1]Sanitaria!K11 -> Porcentaje | ... P196: =[1]Sanitaria!O11 -> Con corte al segundo trimestre de 2024, la fuente de información no ha publicado actualización de los datos posteriores a 2014. | Q196: =[1]Sanitaria!AD11 -> Datos vigentes debido a que la fuente oficial de información no cuenta con actualización de datos.
...
